{"j138973": {"directed": true, "multigraph": false, "graph": {}, "nodes": [{"title": "\u4eba\u4e8b\u4e13\u5458", "id": "j247074"}, {"id": "HR Specialist"}, {"title": "\u4eba\u4e8b\u884c\u653f\u4e13\u5458", "id": "j138973"}, {"title": "\u6025\u8058\uff1a\u9500\u552e\u4e1a\u52a1\u5458", "id": "j167149"}, {"title": "\u4e2d\u533b\u9662\u6536\u8d39\u5458", "id": "j215152"}, {"id": "assistant"}, {"title": "\u884c\u653f\u4eba\u4e8b\u4e13\u5458", "id": "j28993"}, {"id": "business development specialist"}, {"experience": "\u4e92\u8054\u7f51\u53c2\u8003\u6a21\u578bosi\u4e03\u5c42|\u8d44\u6599\u5458\u4e0a\u5c97\u8bc1|\u64cd\u4f5c|\u8d44\u6599|\u4eba\u4e8b\u884c\u653f|\u540e\u53f0|\u9500\u552e\u6280\u80fd|\u7b7e\u8bc1|\u8d22\u52a1|\u4fdd\u7ba1|\u7f16\u5236|\u6587\u6863|\u534f\u52a9|\u7269\u8d44|\u884c\u653f\u5de5\u4f5c|\u767b\u8bb0|\u65bd\u5de5\u73b0\u573a|\u8d44\u6599\u5458|\u8d44\u6599\u7ba1\u7406|\u65bd\u5de5\u56fe", "id": "u3322"}, {"title": "\u9500\u552e\u5185\u52e4", "id": "j20308"}], "links": [{"label": "hasSubType", "source": "j247074", "target": "HR Specialist"}, {"label": "isSubTypeOf", "source": "HR Specialist", "target": "j138973"}, {"label": "hasSubType", "source": "j167149", "target": "assistant"}, {"label": "interactedBy", "source": "j215152", "target": "u3322"}, {"label": "isSubTypeOf", "source": "assistant", "target": "j138973"}, {"label": "isSubTypeOf", "source": "assistant", "target": "j247074"}, {"label": "hasSubType", "source": "j28993", "target": "assistant"}, {"label": "isSubTypeOf", "source": "business development specialist", "target": "j167149"}, {"label": "interactedWith", "source": "u3322", "target": "j20308"}, {"label": "interactedWith", "source": "u3322", "target": "j28993"}, {"label": "interactedWith", "source": "u3322", "target": "j215152"}, {"label": "hasSubType", "source": "j20308", "target": "business development specialist"}]}, "j79949": {"directed": true, "multigraph": false, "graph": {}, "nodes": [{"id": "assistant"}, {"experience": "\u4e92\u8054\u7f51\u53c2\u8003\u6a21\u578bosi\u4e03\u5c42|\u8d44\u6599\u5458\u4e0a\u5c97\u8bc1|\u64cd\u4f5c|\u8d44\u6599|\u4eba\u4e8b\u884c\u653f|\u540e\u53f0|\u9500\u552e\u6280\u80fd|\u7b7e\u8bc1|\u8d22\u52a1|\u4fdd\u7ba1|\u7f16\u5236|\u6587\u6863|\u534f\u52a9|\u7269\u8d44|\u884c\u653f\u5de5\u4f5c|\u767b\u8bb0|\u65bd\u5de5\u73b0\u573a|\u8d44\u6599\u5458|\u8d44\u6599\u7ba1\u7406|\u65bd\u5de5\u56fe", "id": "u3322"}, {"title": "\u4e94\u9669\u4e00\u91d1\u5468\u672b\u53cc\u4f11\u7ecf\u7406\u52a9\u7406/\u4eba\u4e8b", "id": "j79949"}, {"title": "\u884c\u653f\u4eba\u4e8b\u4e13\u5458", "id": "j42760"}, {"title": "\u5185\u52e4\u52a9\u7406", "id": "j79797"}, {"id": "secretary"}, {"title": "\u4eba\u529b\u8d44\u6e90\u4e13\u5458", "id": "j85950"}], "links": [{"label": "isSubTypeOf", "source": "assistant", "target": "j79949"}, {"label": "interactedWith", "source": "u3322", "target": "j85950"}, {"label": "interactedWith", "source": "u3322", "target": "j79797"}, {"label": "interactedWith", "source": "u3322", "target": "j42760"}, {"label": "hasSubType", "source": "j42760", "target": "assistant"}, {"label": "hasSubType", "source": "j79797", "target": "secretary"}, {"label": "isSubTypeOf", "source": "secretary", "target": "j79949"}, {"label": "interactedBy", "source": "j85950", "target": "u3322"}]}, "j128365": {"directed": true, "multigraph": false, "graph": {}, "nodes": [], "links": []}, "j211905": {"directed": true, "multigraph": false, "graph": {}, "nodes": [{"id": "assistant"}, {"title": "\u91c7\u8d2d\u4e13\u5458", "id": "j45998"}, {"id": "Purchasing Specialist"}, {"title": "\u53cc\u4f11+4K\u8058\u65e0\u7ecf\u9a8c\u6280\u672f\u5b9e\u4e60\u751f", "id": "j211905"}, {"experience": "\u4e92\u8054\u7f51\u53c2\u8003\u6a21\u578bosi\u4e03\u5c42|\u8d44\u6599\u5458\u4e0a\u5c97\u8bc1|\u64cd\u4f5c|\u8d44\u6599|\u4eba\u4e8b\u884c\u653f|\u540e\u53f0|\u9500\u552e\u6280\u80fd|\u7b7e\u8bc1|\u8d22\u52a1|\u4fdd\u7ba1|\u7f16\u5236|\u6587\u6863|\u534f\u52a9|\u7269\u8d44|\u884c\u653f\u5de5\u4f5c|\u767b\u8bb0|\u65bd\u5de5\u73b0\u573a|\u8d44\u6599\u5458|\u8d44\u6599\u7ba1\u7406|\u65bd\u5de5\u56fe", "id": "u3322"}, {"title": "\u91c7\u8d2d\u4e13\u5458", "id": "j200927"}], "links": [{"label": "isSubTypeOf", "source": "assistant", "target": "j211905"}, {"label": "hasSubType", "source": "j45998", "target": "assistant"}, {"label": "isSubTypeOf", "source": "Purchasing Specialist", "target": "j45998"}, {"label": "interactedWith", "source": "u3322", "target": "j200927"}, {"label": "hasSubType", "source": "j200927", "target": "Purchasing Specialist"}]}, "j171503": {"directed": true, "multigraph": false, "graph": {}, "nodes": [], "links": []}, "j161294": {"directed": true, "multigraph": false, "graph": {}, "nodes": [{"id": "assist"}, {"id": "Administrative Commissioner"}, {"id": "assistant"}, {"experience": "\u68c0\u9a8c|\u5b89\u6392|\u6587\u4ef6|\u9886\u5bfc|\u68c0\u9a8c\u5de5|\u6267\u884c\u80fd\u529b|\u670d\u52a1\u5458|\u5904\u7406|\u63a5\u5f85|\u9910\u996e|\u534f\u52a9|\u4ea7\u54c1\u8d28\u91cf|\u7f16\u8f91|\u8bb0\u5f55|\u81ea\u6211\u8bc4\u4ef7|\u56e2\u961f\u9886\u5bfc|\u56e2\u961f\u534f\u4f5c|\u52a9\u7406|\u670d\u52a1|\u9002\u5e94\u80fd\u529b|\u5185\u5bb9", "id": "u686"}, {"title": "\u884c\u653f\u4e13\u5458/\u52a9\u7406", "id": "j161294"}, {"id": "business development specialist"}, {"title": "\u9879\u76ee\u7ba1\u57f9\u751f", "id": "j52343"}, {"experience": "\u4e92\u8054\u7f51\u53c2\u8003\u6a21\u578bosi\u4e03\u5c42|\u8d44\u6599\u5458\u4e0a\u5c97\u8bc1|\u64cd\u4f5c|\u8d44\u6599|\u4eba\u4e8b\u884c\u653f|\u540e\u53f0|\u9500\u552e\u6280\u80fd|\u7b7e\u8bc1|\u8d22\u52a1|\u4fdd\u7ba1|\u7f16\u5236|\u6587\u6863|\u534f\u52a9|\u7269\u8d44|\u884c\u653f\u5de5\u4f5c|\u767b\u8bb0|\u65bd\u5de5\u73b0\u573a|\u8d44\u6599\u5458|\u8d44\u6599\u7ba1\u7406|\u65bd\u5de5\u56fe", "id": "u3322"}, {"title": "\u9500\u552e\u5185\u52e4", "id": "j20308"}], "links": [{"label": "isHeldBy", "source": "assist", "target": "u686"}, {"label": "isSubTypeOf", "source": "Administrative Commissioner", "target": "j161294"}, {"label": "isSubTypeOf", "source": "assistant", "target": "j161294"}, {"label": "wantsType", "source": "u686", "target": "Administrative Commissioner"}, {"label": "isSubTypeOf", "source": "business development specialist", "target": "j52343"}, {"label": "hasSubType", "source": "j52343", "target": "assistant"}, {"label": "interactedWith", "source": "u3322", "target": "j20308"}, {"label": "hasSkill", "source": "u3322", "target": "assist"}, {"label": "hasSubType", "source": "j20308", "target": "business development specialist"}]}, "j240522": {"directed": true, "multigraph": false, "graph": {}, "nodes": [{"id": "assistant"}, {"title": "\u884c\u653f\u4e3b\u7ba1", "id": "j57539"}, {"title": "\u6d3b\u52a8\u6267\u884c\u7b56\u5212", "id": "j240522"}, {"experience": "\u4e92\u8054\u7f51\u53c2\u8003\u6a21\u578bosi\u4e03\u5c42|\u8d44\u6599\u5458\u4e0a\u5c97\u8bc1|\u64cd\u4f5c|\u8d44\u6599|\u4eba\u4e8b\u884c\u653f|\u540e\u53f0|\u9500\u552e\u6280\u80fd|\u7b7e\u8bc1|\u8d22\u52a1|\u4fdd\u7ba1|\u7f16\u5236|\u6587\u6863|\u534f\u52a9|\u7269\u8d44|\u884c\u653f\u5de5\u4f5c|\u767b\u8bb0|\u65bd\u5de5\u73b0\u573a|\u8d44\u6599\u5458|\u8d44\u6599\u7ba1\u7406|\u65bd\u5de5\u56fe", "id": "u3322"}, {"title": "\u529e\u516c\u6587\u5458[\u5317\u4eac]", "id": "j219979"}], "links": [{"label": "isSubTypeOf", "source": "assistant", "target": "j240522"}, {"label": "interactedBy", "source": "j57539", "target": "u3322"}, {"label": "interactedWith", "source": "u3322", "target": "j57539"}, {"label": "interactedWith", "source": "u3322", "target": "j219979"}, {"label": "hasSubType", "source": "j219979", "target": "assistant"}]}, "j203824": {"directed": true, "multigraph": false, "graph": {}, "nodes": [{"title": "\u7f51\u7edc\u5728\u7ebf\u5ba2\u670d", "id": "j203824"}, {"id": "network"}, {"title": "\u6dd8\u5b9d\u5ba2\u670d", "id": "j63384"}, {"id": "Pre-sale"}, {"experience": "\u5b66\u4e60|\u6559\u80b2\u5b66|\u4e92\u8054\u7f51\u53c2\u8003\u6a21\u578bosi\u4e03\u5c42|\u5bb6\u957f|\u5b89\u5168|\u4fdd\u969c|\u6c9f\u901a|\u5e7c\u513f|\u5b66\u524d\u6559\u80b2|\u5f69\u5986\u6280\u5de7", "id": "u447"}, {"experience": "\u8d26\u6237|\u652f\u4ed8|\u524d\u7aef\u9875\u9762|\u53f8\u673a|\u524d\u7aef|\u7cfb\u7edf|\u94f6\u884c\u5361|\u5c55\u793a|web\u524d\u7aef|\u8d23\u4efb\u5fc3|his|\u81ea\u6211\u8bc4\u4ef7|\u5e73\u53f0|\u8d39\u7528|\u7a0b\u5e8f\u5458|\u64cd\u4f5c|\u540e\u53f0\u7ba1\u7406|\u8ba1\u4ef7|\u540e\u53f0|\u6ce8\u518c|\u652f\u4ed8\u5b9d\u652f\u4ed8|\u5236\u4f5c|\u7edf\u8ba1|\u533a\u57df|\u62a5\u8868|\u663e\u793a|\u5bc6\u7801|\u4ee3\u7801|\u533b\u7597|sap\u7cfb\u7edf|\u5fae\u4fe1|\u6d88\u8d39|\u7ef4\u62a4", "id": "u1037"}, {"id": "Backstage"}, {"experience": "\u4e92\u8054\u7f51\u53c2\u8003\u6a21\u578bosi\u4e03\u5c42|\u8d44\u6599\u5458\u4e0a\u5c97\u8bc1|\u64cd\u4f5c|\u8d44\u6599|\u4eba\u4e8b\u884c\u653f|\u540e\u53f0|\u9500\u552e\u6280\u80fd|\u7b7e\u8bc1|\u8d22\u52a1|\u4fdd\u7ba1|\u7f16\u5236|\u6587\u6863|\u534f\u52a9|\u7269\u8d44|\u884c\u653f\u5de5\u4f5c|\u767b\u8bb0|\u65bd\u5de5\u73b0\u573a|\u8d44\u6599\u5458|\u8d44\u6599\u7ba1\u7406|\u65bd\u5de5\u56fe", "id": "u3322"}], "links": [{"label": "isSubTypeOf", "source": "network", "target": "j203824"}, {"label": "hasSubType", "source": "j63384", "target": "network"}, {"label": "isWantedTypeOf", "source": "Pre-sale", "target": "u447"}, {"label": "interactedWith", "source": "u447", "target": "j63384"}, {"label": "wantsType", "source": "u1037", "target": "Pre-sale"}, {"label": "isHeldBy", "source": "Backstage", "target": "u1037"}, {"label": "hasSkill", "source": "u3322", "target": "Backstage"}]}, "j110955": {"directed": true, "multigraph": false, "graph": {}, "nodes": [{"title": "\u8d44\u6599\u5458\uff08\u7535\u529b\u3001\u571f\u5efa\uff09", "id": "j149906"}, {"id": "Administrative Commissioner"}, {"title": "\u884c\u653f\u4eba\u4e8b\u4e13\u5458", "id": "j42760"}, {"title": "\u4eba\u529b\u884c\u653f\u4e13\u5458", "id": "j110955"}, {"id": "assistant"}, {"id": "clerk"}, {"title": "\u7ecf\u7406\u52a9\u7406\u79d8\u4e66", "id": "j66462"}, {"title": "\u529e\u516c\u5ba4\u6587\u5458", "id": "j39319"}, {"experience": "\u4e92\u8054\u7f51\u53c2\u8003\u6a21\u578bosi\u4e03\u5c42|\u8d44\u6599\u5458\u4e0a\u5c97\u8bc1|\u64cd\u4f5c|\u8d44\u6599|\u4eba\u4e8b\u884c\u653f|\u540e\u53f0|\u9500\u552e\u6280\u80fd|\u7b7e\u8bc1|\u8d22\u52a1|\u4fdd\u7ba1|\u7f16\u5236|\u6587\u6863|\u534f\u52a9|\u7269\u8d44|\u884c\u653f\u5de5\u4f5c|\u767b\u8bb0|\u65bd\u5de5\u73b0\u573a|\u8d44\u6599\u5458|\u8d44\u6599\u7ba1\u7406|\u65bd\u5de5\u56fe", "id": "u3322"}], "links": [{"label": "interactedBy", "source": "j149906", "target": "u3322"}, {"label": "isSubTypeOf", "source": "Administrative Commissioner", "target": "j110955"}, {"label": "hasSubType", "source": "j42760", "target": "Administrative Commissioner"}, {"label": "isSubTypeOf", "source": "assistant", "target": "j110955"}, {"label": "isSubTypeOf", "source": "clerk", "target": "j39319"}, {"label": "hasSubType", "source": "j66462", "target": "clerk"}, {"label": "hasSubType", "source": "j39319", "target": "assistant"}, {"label": "interactedWith", "source": "u3322", "target": "j149906"}, {"label": "interactedWith", "source": "u3322", "target": "j42760"}, {"label": "interactedWith", "source": "u3322", "target": "j66462"}]}, "j156911": {"directed": true, "multigraph": false, "graph": {}, "nodes": [], "links": []}, "j127843": {"directed": true, "multigraph": false, "graph": {}, "nodes": [{"title": "\u5185\u52e4(\u6587\u5458\uff09", "id": "j206669"}, {"id": "colleges"}, {"experience": "\u5ba2\u670d\u4e13\u5458|\u7535\u8bdd|\u8425\u517b|\u517b\u751f\u4fdd\u5065|\u8425\u517b\u5e08|\u56de\u8bbf|\u63a5\u542c|\u5ba1\u8ba1|\u4eba\u5bff|\u8d22\u52a1|\u4ea7\u54c1|\u8bb0\u5f55|\u6295\u8bc9|\u51cf\u80a5|\u4eba\u5bff\u4fdd\u9669|\u7a0e\u52a1|\u5ba2\u6237", "id": "u1928"}, {"title": "\u884c\u653f\u5185\u52e4", "id": "j127843"}, {"id": "Internal staff"}, {"experience": "\u4e92\u8054\u7f51\u53c2\u8003\u6a21\u578bosi\u4e03\u5c42|\u8d44\u6599\u5458\u4e0a\u5c97\u8bc1|\u64cd\u4f5c|\u8d44\u6599|\u4eba\u4e8b\u884c\u653f|\u540e\u53f0|\u9500\u552e\u6280\u80fd|\u7b7e\u8bc1|\u8d22\u52a1|\u4fdd\u7ba1|\u7f16\u5236|\u6587\u6863|\u534f\u52a9|\u7269\u8d44|\u884c\u653f\u5de5\u4f5c|\u767b\u8bb0|\u65bd\u5de5\u73b0\u573a|\u8d44\u6599\u5458|\u8d44\u6599\u7ba1\u7406|\u65bd\u5de5\u56fe", "id": "u3322"}], "links": [{"label": "hasSubType", "source": "j206669", "target": "Internal staff"}, {"label": "isWantedIndustryOf", "source": "colleges", "target": "u1928"}, {"label": "interactedWith", "source": "u1928", "target": "j206669"}, {"label": "isSubTypeOf", "source": "Internal staff", "target": "j127843"}, {"label": "wantsIndustry", "source": "u3322", "target": "colleges"}]}, "j223923": {"directed": true, "multigraph": false, "graph": {}, "nodes": [], "links": []}, "j239471": {"directed": true, "multigraph": false, "graph": {}, "nodes": [], "links": []}, "7b6f0cd849558574eb8d72ded933a584": {"directed": true, "multigraph": false, "graph": {}, "nodes": [], "links": []}, "j145555": {"directed": true, "multigraph": false, "graph": {}, "nodes": [], "links": []}, "j26214": {"directed": true, "multigraph": false, "graph": {}, "nodes": [{"id": "HR Specialist"}, {"id": "secretary"}, {"title": "\u9879\u76ee\u79d8\u4e66", "id": "j15471"}, {"title": "\u529e\u516c\u6587\u5458[\u5317\u4eac]", "id": "j219979"}, {"title": "\u4eba\u8d44\u884c\u653f\u4e13\u5458", "id": "j157410"}, {"id": "assistant"}, {"title": "\u4eba\u4e8b\u4e13\u5458\u540e\u52e4\u52a9\u7406", "id": "j147172"}, {"id": "clerk"}, {"title": "\u62db\u8058\u6587\u5458\uff08\u65e9\u4e5d\u665a\u516d+\u5468\u672b\u53cc\u4f11+\u4e94\u9669\uff09", "id": "j26214"}, {"experience": "\u4e92\u8054\u7f51\u53c2\u8003\u6a21\u578bosi\u4e03\u5c42|\u8d44\u6599\u5458\u4e0a\u5c97\u8bc1|\u64cd\u4f5c|\u8d44\u6599|\u4eba\u4e8b\u884c\u653f|\u540e\u53f0|\u9500\u552e\u6280\u80fd|\u7b7e\u8bc1|\u8d22\u52a1|\u4fdd\u7ba1|\u7f16\u5236|\u6587\u6863|\u534f\u52a9|\u7269\u8d44|\u884c\u653f\u5de5\u4f5c|\u767b\u8bb0|\u65bd\u5de5\u73b0\u573a|\u8d44\u6599\u5458|\u8d44\u6599\u7ba1\u7406|\u65bd\u5de5\u56fe", "id": "u3322"}], "links": [{"label": "isSubTypeOf", "source": "HR Specialist", "target": "j147172"}, {"label": "isSubTypeOf", "source": "secretary", "target": "j26214"}, {"label": "hasSubType", "source": "j15471", "target": "clerk"}, {"label": "hasSubType", "source": "j219979", "target": "secretary"}, {"label": "hasSubType", "source": "j157410", "target": "HR Specialist"}, {"label": "isSubTypeOf", "source": "assistant", "target": "j26214"}, {"label": "hasSubType", "source": "j147172", "target": "assistant"}, {"label": "isSubTypeOf", "source": "clerk", "target": "j26214"}, {"label": "interactedWith", "source": "u3322", "target": "j157410"}, {"label": "interactedWith", "source": "u3322", "target": "j219979"}, {"label": "interactedWith", "source": "u3322", "target": "j15471"}]}, "j186034": {"directed": true, "multigraph": false, "graph": {}, "nodes": [{"id": "assistant"}, {"title": "\u5e02\u573a\u4e13\u5458", "id": "j197889"}, {"title": "\u5e02\u573a\u4e13\u5458/\u6d3b\u52a8\u6267\u884c\uff08\u8543\u8304\u7530\u957f\u6625\u516d\u5e97\uff09", "id": "j213194"}, {"title": "\u4eba\u4e8b\u62db\u8058\uff08\u5468\u672b\u53cc\u4f11+\u5e74\u5e95\u53cc\u85aa\uff09", "id": "j186034"}, {"id": "Marketing Specialist"}, {"experience": "\u4e92\u8054\u7f51\u53c2\u8003\u6a21\u578bosi\u4e03\u5c42|\u8d44\u6599\u5458\u4e0a\u5c97\u8bc1|\u64cd\u4f5c|\u8d44\u6599|\u4eba\u4e8b\u884c\u653f|\u540e\u53f0|\u9500\u552e\u6280\u80fd|\u7b7e\u8bc1|\u8d22\u52a1|\u4fdd\u7ba1|\u7f16\u5236|\u6587\u6863|\u534f\u52a9|\u7269\u8d44|\u884c\u653f\u5de5\u4f5c|\u767b\u8bb0|\u65bd\u5de5\u73b0\u573a|\u8d44\u6599\u5458|\u8d44\u6599\u7ba1\u7406|\u65bd\u5de5\u56fe", "id": "u3322"}], "links": [{"label": "isSubTypeOf", "source": "assistant", "target": "j186034"}, {"label": "hasSubType", "source": "j197889", "target": "Marketing Specialist"}, {"label": "hasSubType", "source": "j213194", "target": "assistant"}, {"label": "isSubTypeOf", "source": "Marketing Specialist", "target": "j213194"}, {"label": "interactedWith", "source": "u3322", "target": "j197889"}]}, "6f01ddb30a2930cbac818806ef60ea17": {"directed": true, "multigraph": false, "graph": {}, "nodes": [], "links": []}, "j135440": {"directed": true, "multigraph": false, "graph": {}, "nodes": [{"title": "\u4eba\u4e8b\u884c\u653f\u4e13\u5458", "id": "j13044"}, {"title": "\u529e\u516c\u5ba4\u6587\u5458", "id": "j80551"}, {"id": "secretary"}, {"id": "assistant"}, {"id": "clerk"}, {"title": "\u529e\u516c\u5ba4\u52a9\u7406\u6587\u54585\u96691\u91d1", "id": "j135440"}, {"title": "\u8463\u4e8b\u957f\u52a9\u7406", "id": "j257041"}, {"experience": "\u4e92\u8054\u7f51\u53c2\u8003\u6a21\u578bosi\u4e03\u5c42|\u8d44\u6599\u5458\u4e0a\u5c97\u8bc1|\u64cd\u4f5c|\u8d44\u6599|\u4eba\u4e8b\u884c\u653f|\u540e\u53f0|\u9500\u552e\u6280\u80fd|\u7b7e\u8bc1|\u8d22\u52a1|\u4fdd\u7ba1|\u7f16\u5236|\u6587\u6863|\u534f\u52a9|\u7269\u8d44|\u884c\u653f\u5de5\u4f5c|\u767b\u8bb0|\u65bd\u5de5\u73b0\u573a|\u8d44\u6599\u5458|\u8d44\u6599\u7ba1\u7406|\u65bd\u5de5\u56fe", "id": "u3322"}], "links": [{"label": "hasSubType", "source": "j13044", "target": "assistant"}, {"label": "hasSubType", "source": "j80551", "target": "clerk"}, {"label": "isSubTypeOf", "source": "secretary", "target": "j135440"}, {"label": "isSubTypeOf", "source": "assistant", "target": "j135440"}, {"label": "isSubTypeOf", "source": "clerk", "target": "j135440"}, {"label": "hasSubType", "source": "j257041", "target": "secretary"}, {"label": "interactedWith", "source": "u3322", "target": "j80551"}, {"label": "interactedWith", "source": "u3322", "target": "j13044"}, {"label": "interactedWith", "source": "u3322", "target": "j257041"}]}, "j133789": {"directed": true, "multigraph": false, "graph": {}, "nodes": [], "links": []}, "j91559": {"directed": true, "multigraph": false, "graph": {}, "nodes": [{"id": "assistant"}, {"title": "\u8bda\u80584000\u5185\u52e4\u4e94\u9669\u53cc\u4f11", "id": "j91559"}, {"title": "\u884c\u653f\u52a9\u7406", "id": "j249374"}, {"title": "\u4eba\u529b\u884c\u653f\u4e13\u5458", "id": "j110955"}, {"experience": "\u4e92\u8054\u7f51\u53c2\u8003\u6a21\u578bosi\u4e03\u5c42|\u8d44\u6599\u5458\u4e0a\u5c97\u8bc1|\u64cd\u4f5c|\u8d44\u6599|\u4eba\u4e8b\u884c\u653f|\u540e\u53f0|\u9500\u552e\u6280\u80fd|\u7b7e\u8bc1|\u8d22\u52a1|\u4fdd\u7ba1|\u7f16\u5236|\u6587\u6863|\u534f\u52a9|\u7269\u8d44|\u884c\u653f\u5de5\u4f5c|\u767b\u8bb0|\u65bd\u5de5\u73b0\u573a|\u8d44\u6599\u5458|\u8d44\u6599\u7ba1\u7406|\u65bd\u5de5\u56fe", "id": "u3322"}], "links": [{"label": "isSubTypeOf", "source": "assistant", "target": "j91559"}, {"label": "hasSubType", "source": "j249374", "target": "assistant"}, {"label": "interactedBy", "source": "j110955", "target": "u3322"}, {"label": "interactedWith", "source": "u3322", "target": "j249374"}, {"label": "interactedWith", "source": "u3322", "target": "j110955"}]}, "j238971": {"directed": true, "multigraph": false, "graph": {}, "nodes": [], "links": []}, "j201243": {"directed": true, "multigraph": false, "graph": {}, "nodes": [], "links": []}, "j125173": {"directed": true, "multigraph": false, "graph": {}, "nodes": [], "links": []}, "j68821": {"directed": true, "multigraph": false, "graph": {}, "nodes": [{"title": "\u56fe\u4e66\u7ba1\u7406\u5458\uff08\u8ba1\u7b97\u673a\u65b9\u5411\uff09", "id": "j221540"}, {"experience": "\u4e92\u8054\u7f51\u53c2\u8003\u6a21\u578bosi\u4e03\u5c42|\u8d44\u6599\u5458\u4e0a\u5c97\u8bc1|\u64cd\u4f5c|\u8d44\u6599|\u4eba\u4e8b\u884c\u653f|\u540e\u53f0|\u9500\u552e\u6280\u80fd|\u7b7e\u8bc1|\u8d22\u52a1|\u4fdd\u7ba1|\u7f16\u5236|\u6587\u6863|\u534f\u52a9|\u7269\u8d44|\u884c\u653f\u5de5\u4f5c|\u767b\u8bb0|\u65bd\u5de5\u73b0\u573a|\u8d44\u6599\u5458|\u8d44\u6599\u7ba1\u7406|\u65bd\u5de5\u56fe", "id": "u3322"}, {"id": "computer operation"}, {"id": "librarian"}, {"experience": "ce|\u552e\u540e\u670d\u52a1|\u9002\u5e94\u80fd\u529b|office|\u5ba2\u6237\u670d\u52a1|\u6c7d\u8f66\u68c0\u6d4b\u4e0e\u7ef4\u4fee|\u6c7d\u8f66\u914d\u4ef6", "id": "u4163"}, {"title": "\u7eaf\u6587\u804c\u5f55\u5355\u5458\u8f7b\u677e\u53cc\u4f11", "id": "j68821"}, {"title": "\u8d44\u6599\u5f55\u5165\u5458\u53cc\u4f11\u4e94\u9669\u4e00\u91d1", "id": "j96598"}], "links": [{"label": "interactedBy", "source": "j221540", "target": "u4163"}, {"label": "wantsType", "source": "u3322", "target": "librarian"}, {"label": "isSubTypeOf", "source": "computer operation", "target": "j68821"}, {"label": "isSubTypeOf", "source": "librarian", "target": "j221540"}, {"label": "interactedWith", "source": "u4163", "target": "j96598"}, {"label": "hasSubType", "source": "j96598", "target": "computer operation"}]}, "j133258": {"directed": true, "multigraph": false, "graph": {}, "nodes": [], "links": []}, "j117087": {"directed": true, "multigraph": false, "graph": {}, "nodes": [{"title": "\u6587\u5458", "id": "j85426"}, {"title": "3500\u505a\u4e94\u4f11\u4e8c+\u6570\u636e\u6587\u5458/\u52a9\u7406+\u4e94\u9669\u4e00\u91d1", "id": "j117087"}, {"id": "Administrative Commissioner"}, {"title": "\u884c\u653f\u4e13\u5458", "id": "j139110"}, {"title": "\u884c\u653f\u4e13\u5458", "id": "j64717"}, {"id": "assistant"}, {"id": "clerk"}, {"experience": "\u4e92\u8054\u7f51\u53c2\u8003\u6a21\u578bosi\u4e03\u5c42|\u8d44\u6599\u5458\u4e0a\u5c97\u8bc1|\u64cd\u4f5c|\u8d44\u6599|\u4eba\u4e8b\u884c\u653f|\u540e\u53f0|\u9500\u552e\u6280\u80fd|\u7b7e\u8bc1|\u8d22\u52a1|\u4fdd\u7ba1|\u7f16\u5236|\u6587\u6863|\u534f\u52a9|\u7269\u8d44|\u884c\u653f\u5de5\u4f5c|\u767b\u8bb0|\u65bd\u5de5\u73b0\u573a|\u8d44\u6599\u5458|\u8d44\u6599\u7ba1\u7406|\u65bd\u5de5\u56fe", "id": "u3322"}], "links": [{"label": "hasSubType", "source": "j85426", "target": "clerk"}, {"label": "isSubTypeOf", "source": "Administrative Commissioner", "target": "j64717"}, {"label": "hasSubType", "source": "j139110", "target": "Administrative Commissioner"}, {"label": "hasSubType", "source": "j64717", "target": "assistant"}, {"label": "isSubTypeOf", "source": "assistant", "target": "j117087"}, {"label": "isSubTypeOf", "source": "clerk", "target": "j117087"}, {"label": "interactedWith", "source": "u3322", "target": "j85426"}, {"label": "interactedWith", "source": "u3322", "target": "j139110"}]}, "j173773": {"directed": true, "multigraph": false, "graph": {}, "nodes": [], "links": []}, "j59094": {"directed": true, "multigraph": false, "graph": {}, "nodes": [{"id": "assistant"}, {"title": "\u884c\u653f\u52a9\u7406\u7eaf\u6587\u5458\u65e0\u8d233800\u53cc\u4f11", "id": "j59094"}, {"id": "Administrative Commissioner"}, {"title": "\u5546\u54c1\u4e13\u5458", "id": "j155275"}, {"experience": "\u4e92\u8054\u7f51\u53c2\u8003\u6a21\u578bosi\u4e03\u5c42|\u8d44\u6599\u5458\u4e0a\u5c97\u8bc1|\u64cd\u4f5c|\u8d44\u6599|\u4eba\u4e8b\u884c\u653f|\u540e\u53f0|\u9500\u552e\u6280\u80fd|\u7b7e\u8bc1|\u8d22\u52a1|\u4fdd\u7ba1|\u7f16\u5236|\u6587\u6863|\u534f\u52a9|\u7269\u8d44|\u884c\u653f\u5de5\u4f5c|\u767b\u8bb0|\u65bd\u5de5\u73b0\u573a|\u8d44\u6599\u5458|\u8d44\u6599\u7ba1\u7406|\u65bd\u5de5\u56fe", "id": "u3322"}, {"title": "\u884c\u653f", "id": "j185458"}], "links": [{"label": "isSubTypeOf", "source": "assistant", "target": "j59094"}, {"label": "isSubTypeOf", "source": "Administrative Commissioner", "target": "j59094"}, {"label": "hasSubType", "source": "j155275", "target": "assistant"}, {"label": "interactedWith", "source": "u3322", "target": "j155275"}, {"label": "interactedWith", "source": "u3322", "target": "j185458"}, {"label": "hasSubType", "source": "j185458", "target": "Administrative Commissioner"}]}, "j219732": {"directed": true, "multigraph": false, "graph": {}, "nodes": [], "links": []}, "j55363": {"directed": true, "multigraph": false, "graph": {}, "nodes": [{"title": "\u884c\u653f\u7ecf\u7406\u52a9\u7406\u7a33\u5b9a\u53cc\u4f11\u4e0d\u52a0\u73ed", "id": "j55363"}, {"title": "\u884c\u653f\u52a9\u7406", "id": "j249374"}, {"id": "Administrative Commissioner"}, {"title": "\u84dd\u6708\u4eae\u8bda\u8058\u5510\u5c71\u4eba\u4e8b\u4e13\u5458", "id": "j206488"}, {"id": "assistant"}, {"title": "\u5185\u4e1a\u8d44\u6599\u5458", "id": "j247938"}, {"experience": "\u4e92\u8054\u7f51\u53c2\u8003\u6a21\u578bosi\u4e03\u5c42|\u8d44\u6599\u5458\u4e0a\u5c97\u8bc1|\u64cd\u4f5c|\u8d44\u6599|\u4eba\u4e8b\u884c\u653f|\u540e\u53f0|\u9500\u552e\u6280\u80fd|\u7b7e\u8bc1|\u8d22\u52a1|\u4fdd\u7ba1|\u7f16\u5236|\u6587\u6863|\u534f\u52a9|\u7269\u8d44|\u884c\u653f\u5de5\u4f5c|\u767b\u8bb0|\u65bd\u5de5\u73b0\u573a|\u8d44\u6599\u5458|\u8d44\u6599\u7ba1\u7406|\u65bd\u5de5\u56fe", "id": "u3322"}, {"title": "\u9500\u552e\u5185\u52e4", "id": "j20308"}], "links": [{"label": "hasSubType", "source": "j249374", "target": "Administrative Commissioner"}, {"label": "isSubTypeOf", "source": "Administrative Commissioner", "target": "j55363"}, {"label": "interactedBy", "source": "j206488", "target": "u3322"}, {"label": "isSubTypeOf", "source": "assistant", "target": "j55363"}, {"label": "interactedBy", "source": "j247938", "target": "u3322"}, {"label": "interactedWith", "source": "u3322", "target": "j249374"}, {"label": "interactedWith", "source": "u3322", "target": "j20308"}, {"label": "interactedWith", "source": "u3322", "target": "j247938"}, {"label": "interactedWith", "source": "u3322", "target": "j206488"}, {"label": "hasSubType", "source": "j20308", "target": "assistant"}]}, "j31650": {"directed": true, "multigraph": false, "graph": {}, "nodes": [], "links": []}, "j45235": {"directed": true, "multigraph": false, "graph": {}, "nodes": [], "links": []}, "b5883daea7e63cb2683b0342b90f82c4": {"directed": true, "multigraph": false, "graph": {}, "nodes": [], "links": []}, "j47383": {"directed": true, "multigraph": false, "graph": {}, "nodes": [], "links": []}, "j191064": {"directed": true, "multigraph": false, "graph": {}, "nodes": [], "links": []}, "j47416": {"directed": true, "multigraph": false, "graph": {}, "nodes": [{"id": "assistant"}, {"id": "HR Specialist"}, {"title": "\u884c\u653f\u4e13\u5458", "id": "j47416"}, {"title": "\u884c\u653f\u4eba\u4e8b\u4e13\u5458", "id": "j28993"}, {"title": "HRBP(\u7528\u6237\u4f53\u9a8c\u7aef\uff09", "id": "j76558"}, {"experience": "\u4e92\u8054\u7f51\u53c2\u8003\u6a21\u578bosi\u4e03\u5c42|\u8d44\u6599\u5458\u4e0a\u5c97\u8bc1|\u64cd\u4f5c|\u8d44\u6599|\u4eba\u4e8b\u884c\u653f|\u540e\u53f0|\u9500\u552e\u6280\u80fd|\u7b7e\u8bc1|\u8d22\u52a1|\u4fdd\u7ba1|\u7f16\u5236|\u6587\u6863|\u534f\u52a9|\u7269\u8d44|\u884c\u653f\u5de5\u4f5c|\u767b\u8bb0|\u65bd\u5de5\u73b0\u573a|\u8d44\u6599\u5458|\u8d44\u6599\u7ba1\u7406|\u65bd\u5de5\u56fe", "id": "u3322"}], "links": [{"label": "isSubTypeOf", "source": "assistant", "target": "j47416"}, {"label": "isSubTypeOf", "source": "HR Specialist", "target": "j76558"}, {"label": "hasSubType", "source": "j28993", "target": "HR Specialist"}, {"label": "hasSubType", "source": "j76558", "target": "assistant"}, {"label": "interactedWith", "source": "u3322", "target": "j28993"}]}, "j224634": {"directed": true, "multigraph": false, "graph": {}, "nodes": [{"id": "\\N"}, {"title": "\u623f\u8d37\u52a9\u7406", "id": "j84419"}, {"experience": "\u4e92\u8054\u7f51\u53c2\u8003\u6a21\u578bosi\u4e03\u5c42|\u8d44\u6599\u5458\u4e0a\u5c97\u8bc1|\u64cd\u4f5c|\u8d44\u6599|\u4eba\u4e8b\u884c\u653f|\u540e\u53f0|\u9500\u552e\u6280\u80fd|\u7b7e\u8bc1|\u8d22\u52a1|\u4fdd\u7ba1|\u7f16\u5236|\u6587\u6863|\u534f\u52a9|\u7269\u8d44|\u884c\u653f\u5de5\u4f5c|\u767b\u8bb0|\u65bd\u5de5\u73b0\u573a|\u8d44\u6599\u5458|\u8d44\u6599\u7ba1\u7406|\u65bd\u5de5\u56fe", "id": "u3322"}, {"title": "\u5c1a\u5fb7\u673a\u6784\u9ad8\u85aa\u76f4\u8058\u8bfe\u7a0b\u987e\u95ee/\u7535\u8bdd\u9500\u552e", "id": "j224634"}], "links": [{"label": "isSubTypeOf", "source": "\\N", "target": "j224634"}, {"label": "hasSubType", "source": "j84419", "target": "\\N"}, {"label": "interactedWith", "source": "u3322", "target": "j84419"}]}, "j139827": {"directed": true, "multigraph": false, "graph": {}, "nodes": [], "links": []}, "j81297": {"directed": true, "multigraph": false, "graph": {}, "nodes": [{"id": "assistant"}, {"title": "3000-5000+\u4e94\u9669\u6025\u8058\u5ba2\u670d\u4e13\u5458", "id": "j81297"}, {"experience": "\u8ba1\u5212|\u6863\u6848\u7ba1\u7406|\u9884\u7b97|\u884c\u653f\u4e3b\u7ba1|\u529e\u516c|\u7ba1\u7406\u5236\u5ea6|\u7ba1\u7406|\u7ec4\u7ec7|\u63a5\u5f85|\u8bbe\u5907|\u767b\u8bb0|\u7b79\u5907|\u5b89\u6392|\u9886\u5bfc|\u6536\u96c6\u6574\u7406|\u6d88\u9632|\u4fdd\u536b|\u68c0\u67e5|\u534f\u8c03\u80fd\u529b|\u91c7\u8d2d\u7ba1\u7406|\u4e3b\u6301|\u56e2\u961f\u9886\u5bfc|\u5bf9\u5916|\u884c\u653f\u5de5\u4f5c|\u884c\u653f\u7ba1\u7406|\u5b66\u4e60\u80fd\u529b|\u73af\u5883|\u573a\u5730|\u63a8\u8fdb|\u6587\u4ef6|\u6863\u6848|\u6267\u884c|\u884c\u653f\u7ecf\u7406|\u79df\u8d41|\u4e3b\u7ba1|\u50a8\u5907\u5e72\u90e8|\u7763\u5bdf|\u91c7\u8d2d|\u5b9e\u65bd|\u8bc1\u7167|\u8d44\u6599\u7ba1\u7406|\u5ba2\u6237|\u4f1a\u8bae|\u884c\u653f|\u6d41\u7a0b|\u529e\u516c\u5ba4\u4e3b\u4efb|\u7f16\u5236|\u8f66\u8f86|\u8d44\u4ea7|\u5ba1\u6279|\u5b89\u5168|\u8d44\u8d28|\u9002\u5e94\u80fd\u529b|\u5370\u7ae0|\u6d88\u9632\u62a4\u536b", "id": "u3733"}, {"id": "administrative work"}, {"experience": "\u4e92\u8054\u7f51\u53c2\u8003\u6a21\u578bosi\u4e03\u5c42|\u8d44\u6599\u5458\u4e0a\u5c97\u8bc1|\u64cd\u4f5c|\u8d44\u6599|\u4eba\u4e8b\u884c\u653f|\u540e\u53f0|\u9500\u552e\u6280\u80fd|\u7b7e\u8bc1|\u8d22\u52a1|\u4fdd\u7ba1|\u7f16\u5236|\u6587\u6863|\u534f\u52a9|\u7269\u8d44|\u884c\u653f\u5de5\u4f5c|\u767b\u8bb0|\u65bd\u5de5\u73b0\u573a|\u8d44\u6599\u5458|\u8d44\u6599\u7ba1\u7406|\u65bd\u5de5\u56fe", "id": "u3322"}], "links": [{"label": "isSubTypeOf", "source": "assistant", "target": "j81297"}, {"label": "wantsType", "source": "u3733", "target": "assistant"}, {"label": "isHeldBy", "source": "administrative work", "target": "u3733"}, {"label": "hasSkill", "source": "u3322", "target": "administrative work"}]}, "j155481": {"directed": true, "multigraph": false, "graph": {}, "nodes": [], "links": []}, "j116701": {"directed": true, "multigraph": false, "graph": {}, "nodes": [], "links": []}, "j6074": {"directed": true, "multigraph": false, "graph": {}, "nodes": [], "links": []}, "j92887": {"directed": true, "multigraph": false, "graph": {}, "nodes": [], "links": []}, "j53443": {"directed": true, "multigraph": false, "graph": {}, "nodes": [{"id": "assistant"}, {"title": "\u7ecf\u7406\u52a9\u7406\u5468\u672b\u53cc\u4f11", "id": "j216327"}, {"title": "\u65b0\u5a92\u4f53\u8fd0\u8425", "id": "j33110"}, {"id": "HR Specialist"}, {"title": "\u4eba\u4e8b\u4e13\u5458", "id": "j53443"}, {"experience": "\u4e92\u8054\u7f51\u53c2\u8003\u6a21\u578bosi\u4e03\u5c42|\u8d44\u6599\u5458\u4e0a\u5c97\u8bc1|\u64cd\u4f5c|\u8d44\u6599|\u4eba\u4e8b\u884c\u653f|\u540e\u53f0|\u9500\u552e\u6280\u80fd|\u7b7e\u8bc1|\u8d22\u52a1|\u4fdd\u7ba1|\u7f16\u5236|\u6587\u6863|\u534f\u52a9|\u7269\u8d44|\u884c\u653f\u5de5\u4f5c|\u767b\u8bb0|\u65bd\u5de5\u73b0\u573a|\u8d44\u6599\u5458|\u8d44\u6599\u7ba1\u7406|\u65bd\u5de5\u56fe", "id": "u3322"}, {"title": "\u4eba\u529b\u8d44\u6e90\u4e13\u5458", "id": "j85950"}], "links": [{"label": "isSubTypeOf", "source": "assistant", "target": "j53443"}, {"label": "hasSubType", "source": "j216327", "target": "assistant"}, {"label": "interactedBy", "source": "j33110", "target": "u3322"}, {"label": "isSubTypeOf", "source": "HR Specialist", "target": "j53443"}, {"label": "interactedWith", "source": "u3322", "target": "j216327"}, {"label": "interactedWith", "source": "u3322", "target": "j85950"}, {"label": "interactedWith", "source": "u3322", "target": "j33110"}, {"label": "hasSubType", "source": "j85950", "target": "HR Specialist"}]}, "j96634": {"directed": true, "multigraph": false, "graph": {}, "nodes": [], "links": []}, "j49691": {"directed": true, "multigraph": false, "graph": {}, "nodes": [{"id": "assistant"}, {"title": "\u884c\u653f\u4eba\u4e8b\u4e13\u5458", "id": "j42760"}, {"title": "\u8463\u4e8b\u957f\u52a9\u7406", "id": "j257041"}, {"title": "\u4eba\u4e8b\u4e13\u5458", "id": "j49691"}, {"experience": "\u4e92\u8054\u7f51\u53c2\u8003\u6a21\u578bosi\u4e03\u5c42|\u8d44\u6599\u5458\u4e0a\u5c97\u8bc1|\u64cd\u4f5c|\u8d44\u6599|\u4eba\u4e8b\u884c\u653f|\u540e\u53f0|\u9500\u552e\u6280\u80fd|\u7b7e\u8bc1|\u8d22\u52a1|\u4fdd\u7ba1|\u7f16\u5236|\u6587\u6863|\u534f\u52a9|\u7269\u8d44|\u884c\u653f\u5de5\u4f5c|\u767b\u8bb0|\u65bd\u5de5\u73b0\u573a|\u8d44\u6599\u5458|\u8d44\u6599\u7ba1\u7406|\u65bd\u5de5\u56fe", "id": "u3322"}], "links": [{"label": "isSubTypeOf", "source": "assistant", "target": "j49691"}, {"label": "interactedBy", "source": "j42760", "target": "u3322"}, {"label": "hasSubType", "source": "j257041", "target": "assistant"}, {"label": "interactedWith", "source": "u3322", "target": "j42760"}, {"label": "interactedWith", "source": "u3322", "target": "j257041"}]}, "j218894": {"directed": true, "multigraph": false, "graph": {}, "nodes": [], "links": []}, "j244150": {"directed": true, "multigraph": false, "graph": {}, "nodes": [{"title": "\u4eba\u529b\u8d44\u6e90\u52b3\u52a8\u5173\u7cfb\u4e13\u5458", "id": "j5086"}, {"id": "HR Specialist"}, {"title": "\u4eba\u4e8b\u884c\u653f\u6587\u5458", "id": "j219750"}, {"id": "Administrative Commissioner"}, {"title": "\u884c\u653f\u524d\u53f0", "id": "j137049"}, {"title": "\u4eba\u4e8b\u4e13\u5458", "id": "j244150"}, {"title": "\u84dd\u6708\u4eae\u8bda\u8058\u5510\u5c71\u4eba\u4e8b\u4e13\u5458", "id": "j206488"}, {"id": "assistant"}, {"experience": "\u4e92\u8054\u7f51\u53c2\u8003\u6a21\u578bosi\u4e03\u5c42|\u8d44\u6599\u5458\u4e0a\u5c97\u8bc1|\u64cd\u4f5c|\u8d44\u6599|\u4eba\u4e8b\u884c\u653f|\u540e\u53f0|\u9500\u552e\u6280\u80fd|\u7b7e\u8bc1|\u8d22\u52a1|\u4fdd\u7ba1|\u7f16\u5236|\u6587\u6863|\u534f\u52a9|\u7269\u8d44|\u884c\u653f\u5de5\u4f5c|\u767b\u8bb0|\u65bd\u5de5\u73b0\u573a|\u8d44\u6599\u5458|\u8d44\u6599\u7ba1\u7406|\u65bd\u5de5\u56fe", "id": "u3322"}], "links": [{"label": "hasSubType", "source": "j5086", "target": "HR Specialist"}, {"label": "isSubTypeOf", "source": "HR Specialist", "target": "j244150"}, {"label": "hasSubType", "source": "j219750", "target": "Administrative Commissioner"}, {"label": "isSubTypeOf", "source": "Administrative Commissioner", "target": "j137049"}, {"label": "hasSubType", "source": "j137049", "target": "assistant"}, {"label": "hasSubType", "source": "j206488", "target": "assistant"}, {"label": "isSubTypeOf", "source": "assistant", "target": "j5086"}, {"label": "isSubTypeOf", "source": "assistant", "target": "j244150"}, {"label": "interactedWith", "source": "u3322", "target": "j219750"}, {"label": "interactedWith", "source": "u3322", "target": "j206488"}]}, "j219480": {"directed": true, "multigraph": false, "graph": {}, "nodes": [{"id": "assistant"}, {"id": "b131dd45df3298b0696df84a660a53c6"}, {"experience": "\u4e92\u8054\u7f51\u53c2\u8003\u6a21\u578bosi\u4e03\u5c42|\u8d44\u6599\u5458\u4e0a\u5c97\u8bc1|\u64cd\u4f5c|\u8d44\u6599|\u4eba\u4e8b\u884c\u653f|\u540e\u53f0|\u9500\u552e\u6280\u80fd|\u7b7e\u8bc1|\u8d22\u52a1|\u4fdd\u7ba1|\u7f16\u5236|\u6587\u6863|\u534f\u52a9|\u7269\u8d44|\u884c\u653f\u5de5\u4f5c|\u767b\u8bb0|\u65bd\u5de5\u73b0\u573a|\u8d44\u6599\u5458|\u8d44\u6599\u7ba1\u7406|\u65bd\u5de5\u56fe", "id": "u3322"}, {"title": "\u4eba\u4e8b\u884c\u653f\u4e13\u5458", "id": "j219480"}, {"id": "operate"}, {"experience": "\u8ba1\u5212|\u5206\u6790|\u4e92\u8054\u7f51\u53c2\u8003\u6a21\u578bosi\u4e03\u5c42|\u5e97\u957f|\u8fd0\u8425|\u5458\u5de5|\u6807\u51c6\u5316|\u5904\u7406|\u85aa\u8d44|office|\u9910\u996e|\u8fd0\u8425\u603b\u76d1|\u603b\u7ecf\u529e|\u6838\u7b97|\u6570\u636e\u5206\u6790|\u57f9\u8bad\u7763\u5bfc|\u589e\u503c|\u5ba3\u4f20|\u6295\u8bc9|\u90ae\u4ef6|\u6536\u96c6|\u8fd0\u4f5c|\u4f1a\u8bae|\u57f9\u8bad|\u5168\u56fd|\u516c\u4f17|\u63a8\u8350|\u8d22\u52a1\u7ba1\u7406|\u8bfe\u4ef6|\u9500\u552e\u6280\u80fd|\u4e3b\u6301|\u533a\u57df|\u534f\u52a9|\u7ee9\u6548|\u7b56\u5212|\u6548\u7387|\u4ea7\u54c1|\u7f16\u8f91|\u8d1f\u8d23\u4eba|\u5fae\u4fe1\u516c\u4f17\u53f7\u8fd0\u8425\u7ba1\u7406|\u4f18\u5316|\u52a9\u7406|\u5fae\u4fe1|\u5927\u533a|\u670d\u52a1|\u9500\u552e|\u63a5\u6536|\u652f\u6301", "id": "u4302"}], "links": [{"label": "isSubTypeOf", "source": "assistant", "target": "j219480"}, {"label": "interactedBy", "source": "b131dd45df3298b0696df84a660a53c6", "target": "u3322"}, {"label": "interactedWith", "source": "u3322", "target": "b131dd45df3298b0696df84a660a53c6"}, {"label": "hasSkill", "source": "u3322", "target": "operate"}, {"label": "isHeldBy", "source": "operate", "target": "u4302"}, {"label": "hasSkill", "source": "u4302", "target": "assistant"}]}, "j84715": {"directed": true, "multigraph": false, "graph": {}, "nodes": [{"title": "\u884c\u653f\u4eba\u4e8b\u52a9\u7406", "id": "j38280"}, {"id": "assistant"}, {"title": "\u6863\u6848/\u8d44\u6599\u7ba1\u7406", "id": "j122478"}, {"id": "librarian"}, {"experience": "\u8d23\u4efb\u5fc3|\u6821\u56ed|\u4e92\u8054\u7f51\u53c2\u8003\u6a21\u578bosi\u4e03\u5c42|\u56e2\u961f\u9886\u5bfc|\u8001\u5e08|\u89c1\u4e60", "id": "u2147"}, {"title": "\u5510\u5c71\u516c\u53f8\u6025\u62db\u730e\u5934\u52a9\u7406|\u730e\u5934\u987e\u95ee", "id": "j84715"}, {"experience": "\u4e92\u8054\u7f51\u53c2\u8003\u6a21\u578bosi\u4e03\u5c42|\u8d44\u6599\u5458\u4e0a\u5c97\u8bc1|\u64cd\u4f5c|\u8d44\u6599|\u4eba\u4e8b\u884c\u653f|\u540e\u53f0|\u9500\u552e\u6280\u80fd|\u7b7e\u8bc1|\u8d22\u52a1|\u4fdd\u7ba1|\u7f16\u5236|\u6587\u6863|\u534f\u52a9|\u7269\u8d44|\u884c\u653f\u5de5\u4f5c|\u767b\u8bb0|\u65bd\u5de5\u73b0\u573a|\u8d44\u6599\u5458|\u8d44\u6599\u7ba1\u7406|\u65bd\u5de5\u56fe", "id": "u3322"}], "links": [{"label": "hasSubType", "source": "j38280", "target": "assistant"}, {"label": "isSubTypeOf", "source": "assistant", "target": "j84715"}, {"label": "interactedBy", "source": "j122478", "target": "u2147"}, {"label": "isSubTypeOf", "source": "librarian", "target": "j122478"}, {"label": "interactedWith", "source": "u2147", "target": "j38280"}, {"label": "wantsType", "source": "u3322", "target": "librarian"}]}, "j31419": {"directed": true, "multigraph": false, "graph": {}, "nodes": [{"experience": "\u4e92\u8054\u7f51\u53c2\u8003\u6a21\u578bosi\u4e03\u5c42|\u5bb6\u957f|\u8003\u8bd5|\u6559\u5e08|\u5b66\u7ba1\u5e08|\u5b66\u4e60|\u73ed\u4e3b\u4efb|\u5b66\u751f|\u6c9f\u901a|\u804c\u80fd\u90e8\u95e8|\u6307\u5bfc|\u4eba\u529b\u8d44\u6e90|\u4e8b\u52a1", "id": "u812"}, {"title": "\u4eba\u4e8b\u4e13\u5458", "id": "j31419"}, {"id": "HR Specialist"}, {"id": "Administrative Commissioner"}, {"experience": "\u4e92\u8054\u7f51\u53c2\u8003\u6a21\u578bosi\u4e03\u5c42|\u540e\u52e4\u4fdd\u969c|\u5458\u5de5|\u79e9\u5e8f|\u884c\u653f\u52a9\u7406|\u63a5\u5f85|\u4e1a\u52a1|\u8003\u52e4|\u5408\u540c|\u9700\u6c42|\u5199\u5b57|\u767b\u8bb0|\u8d44\u6599\u7ba1\u7406|\u5ba2\u6237|\u7269\u6599|\u4f4f\u5b85|\u5ba2\u6237\u5173\u7cfb|\u5ba2\u6237\u7ef4\u62a4|\u5199\u5b57\u697c|\u7ebf\u4e0b|\u9886\u5bfc|\u7ebf\u4e0a|\u7b7e\u7ea6|\u4e70\u5356|\u54a8\u8be2|\u6253\u5370|\u6570\u636e|\u4ea7\u54c1|\u8bc6\u522b|\u623f\u4ea7\u7ecf\u7eaa\u4eba|\u5f55\u5165|\u5546\u94fa|\u7ef4\u62a4", "id": "u3606"}, {"title": "\u4eba\u529b\u8d44\u6e90\u4e13\u5458", "id": "j85950"}, {"title": "\u4eba\u4e8b\u4e13\u5458", "id": "j264129"}, {"title": "\u884c\u653f", "id": "j185458"}, {"id": "assistant"}, {"title": "\u884c\u653f\u6587\u54583K+\u5305\u98df\u5bbf+\u5e26\u85aa\u57f9\u8bad", "id": "j7976"}, {"id": "building materials"}, {"experience": "\u4e92\u8054\u7f51\u53c2\u8003\u6a21\u578bosi\u4e03\u5c42|\u8d44\u6599\u5458\u4e0a\u5c97\u8bc1|\u64cd\u4f5c|\u8d44\u6599|\u4eba\u4e8b\u884c\u653f|\u540e\u53f0|\u9500\u552e\u6280\u80fd|\u7b7e\u8bc1|\u8d22\u52a1|\u4fdd\u7ba1|\u7f16\u5236|\u6587\u6863|\u534f\u52a9|\u7269\u8d44|\u884c\u653f\u5de5\u4f5c|\u767b\u8bb0|\u65bd\u5de5\u73b0\u573a|\u8d44\u6599\u5458|\u8d44\u6599\u7ba1\u7406|\u65bd\u5de5\u56fe", "id": "u3322"}], "links": [{"label": "interactedWith", "source": "u812", "target": "j31419"}, {"label": "isSubTypeOf", "source": "HR Specialist", "target": "j31419"}, {"label": "isSubTypeOf", "source": "Administrative Commissioner", "target": "j7976"}, {"label": "interactedWith", "source": "u3606", "target": "j264129"}, {"label": "interactedBy", "source": "j85950", "target": "u812"}, {"label": "hasSubType", "source": "j264129", "target": "HR Specialist"}, {"label": "hasSubType", "source": "j185458", "target": "Administrative Commissioner"}, {"label": "isSubTypeOf", "source": "assistant", "target": "j31419"}, {"label": "hasSubType", "source": "j7976", "target": "assistant"}, {"label": "isCurrentIndustryOf", "source": "building materials", "target": "u3606"}, {"label": "interactedWith", "source": "u3322", "target": "j85950"}, {"label": "interactedWith", "source": "u3322", "target": "j185458"}, {"label": "wantsIndustry", "source": "u3322", "target": "building materials"}]}, "j117373": {"directed": true, "multigraph": false, "graph": {}, "nodes": [{"id": "assistant"}, {"title": "\u6587\u5458", "id": "j68547"}, {"title": "\u7efc\u5408\u4eba\u4e8b\u5c97", "id": "j117373"}, {"id": "secretary"}, {"experience": "\u4e92\u8054\u7f51\u53c2\u8003\u6a21\u578bosi\u4e03\u5c42|\u8d44\u6599\u5458\u4e0a\u5c97\u8bc1|\u64cd\u4f5c|\u8d44\u6599|\u4eba\u4e8b\u884c\u653f|\u540e\u53f0|\u9500\u552e\u6280\u80fd|\u7b7e\u8bc1|\u8d22\u52a1|\u4fdd\u7ba1|\u7f16\u5236|\u6587\u6863|\u534f\u52a9|\u7269\u8d44|\u884c\u653f\u5de5\u4f5c|\u767b\u8bb0|\u65bd\u5de5\u73b0\u573a|\u8d44\u6599\u5458|\u8d44\u6599\u7ba1\u7406|\u65bd\u5de5\u56fe", "id": "u3322"}, {"title": "\u9879\u76ee\u79d8\u4e66", "id": "j15471"}], "links": [{"label": "isSubTypeOf", "source": "assistant", "target": "j117373"}, {"label": "hasSubType", "source": "j68547", "target": "assistant"}, {"label": "isSubTypeOf", "source": "secretary", "target": "j68547"}, {"label": "interactedWith", "source": "u3322", "target": "j15471"}, {"label": "hasSubType", "source": "j15471", "target": "secretary"}]}, "j202629": {"directed": true, "multigraph": false, "graph": {}, "nodes": [{"id": "assistant"}, {"id": "Logistic specialist"}, {"title": "\u4eba\u4e8b\u4e13\u5458", "id": "j53443"}, {"title": "\u3010\u5510\u5c71\u3011\u7269\u6d41\u4e13\u5458/\u52a9\u7406", "id": "j202629"}, {"title": "\u7269\u6d41\u4e13\u5458\uff08\u6e1d\u5317\uff09", "id": "j33054"}, {"experience": "\u4e92\u8054\u7f51\u53c2\u8003\u6a21\u578bosi\u4e03\u5c42|\u8d44\u6599\u5458\u4e0a\u5c97\u8bc1|\u64cd\u4f5c|\u8d44\u6599|\u4eba\u4e8b\u884c\u653f|\u540e\u53f0|\u9500\u552e\u6280\u80fd|\u7b7e\u8bc1|\u8d22\u52a1|\u4fdd\u7ba1|\u7f16\u5236|\u6587\u6863|\u534f\u52a9|\u7269\u8d44|\u884c\u653f\u5de5\u4f5c|\u767b\u8bb0|\u65bd\u5de5\u73b0\u573a|\u8d44\u6599\u5458|\u8d44\u6599\u7ba1\u7406|\u65bd\u5de5\u56fe", "id": "u3322"}, {"title": "\u884c\u653f", "id": "j185458"}], "links": [{"label": "isSubTypeOf", "source": "assistant", "target": "j33054"}, {"label": "isSubTypeOf", "source": "assistant", "target": "j202629"}, {"label": "isSubTypeOf", "source": "Logistic specialist", "target": "j202629"}, {"label": "hasSubType", "source": "j53443", "target": "assistant"}, {"label": "hasSubType", "source": "j33054", "target": "Logistic specialist"}, {"label": "interactedWith", "source": "u3322", "target": "j53443"}, {"label": "interactedWith", "source": "u3322", "target": "j185458"}, {"label": "hasSubType", "source": "j185458", "target": "assistant"}]}, "j101078": {"directed": true, "multigraph": false, "graph": {}, "nodes": [{"id": "assistant"}, {"id": "HR Specialist"}, {"title": "\u884c\u653f\u4eba\u4e8b\u4e13\u5458", "id": "j28993"}, {"title": "\u96c6\u56e2\u4eba\u8d44\u884c\u653f\u4e13\u5458", "id": "j3320"}, {"experience": "\u4e92\u8054\u7f51\u53c2\u8003\u6a21\u578bosi\u4e03\u5c42|\u8d44\u6599\u5458\u4e0a\u5c97\u8bc1|\u64cd\u4f5c|\u8d44\u6599|\u4eba\u4e8b\u884c\u653f|\u540e\u53f0|\u9500\u552e\u6280\u80fd|\u7b7e\u8bc1|\u8d22\u52a1|\u4fdd\u7ba1|\u7f16\u5236|\u6587\u6863|\u534f\u52a9|\u7269\u8d44|\u884c\u653f\u5de5\u4f5c|\u767b\u8bb0|\u65bd\u5de5\u73b0\u573a|\u8d44\u6599\u5458|\u8d44\u6599\u7ba1\u7406|\u65bd\u5de5\u56fe", "id": "u3322"}, {"title": "\u4eba\u4e8b\u4e13\u5458", "id": "j101078"}], "links": [{"label": "isSubTypeOf", "source": "assistant", "target": "j101078"}, {"label": "isSubTypeOf", "source": "HR Specialist", "target": "j101078"}, {"label": "hasSubType", "source": "j28993", "target": "HR Specialist"}, {"label": "hasSubType", "source": "j3320", "target": "assistant"}, {"label": "interactedWith", "source": "u3322", "target": "j28993"}, {"label": "interactedWith", "source": "u3322", "target": "j3320"}]}, "j241051": {"directed": true, "multigraph": false, "graph": {}, "nodes": [{"title": "\u884c\u653f\u4e3b\u7ba1", "id": "j57539"}, {"experience": "\u4e92\u8054\u7f51\u53c2\u8003\u6a21\u578bosi\u4e03\u5c42|\u8d44\u6599\u5458\u4e0a\u5c97\u8bc1|\u64cd\u4f5c|\u8d44\u6599|\u4eba\u4e8b\u884c\u653f|\u540e\u53f0|\u9500\u552e\u6280\u80fd|\u7b7e\u8bc1|\u8d22\u52a1|\u4fdd\u7ba1|\u7f16\u5236|\u6587\u6863|\u534f\u52a9|\u7269\u8d44|\u884c\u653f\u5de5\u4f5c|\u767b\u8bb0|\u65bd\u5de5\u73b0\u573a|\u8d44\u6599\u5458|\u8d44\u6599\u7ba1\u7406|\u65bd\u5de5\u56fe", "id": "u3322"}, {"id": "director"}, {"title": "\u91c7\u8d2d\u4e3b\u7ba1", "id": "j241051"}], "links": [{"label": "hasSubType", "source": "j57539", "target": "director"}, {"label": "interactedWith", "source": "u3322", "target": "j57539"}, {"label": "isSubTypeOf", "source": "director", "target": "j241051"}]}, "j14372": {"directed": true, "multigraph": false, "graph": {}, "nodes": [{"title": "\u8fd0\u8425\u90e8\u524d\u53f0\u63a5\u5f85", "id": "j47415"}, {"title": "\u884c\u653f\u524d\u53f0\u6587\u5458", "id": "j14372"}, {"title": "\u8d44\u6599\u7ba1\u7406\uff08\u7eaf\u6587\u804c+\u8f7b\u677e\uff09", "id": "j115425"}, {"title": "\u884c\u653f\u524d\u53f0(6\u5c0f\u65f6\u5de5\u4f5c\u5236+\u671d\u4e5d\u665a\u4e94+\u5468\u672b\u53cc\u4f11)", "id": "j145676"}, {"title": "\u884c\u653f\u524d\u53f0\uff08\u5468\u672b\u53cc\u4f11+\u516d\u9669\u4e00\u91d1+\u5341\u4e09\u85aa\uff09", "id": "j117038"}, {"id": "front desk"}, {"id": "reception"}, {"experience": "\u4e92\u8054\u7f51\u53c2\u8003\u6a21\u578bosi\u4e03\u5c42|\u8d44\u6599\u5458\u4e0a\u5c97\u8bc1|\u64cd\u4f5c|\u8d44\u6599|\u4eba\u4e8b\u884c\u653f|\u540e\u53f0|\u9500\u552e\u6280\u80fd|\u7b7e\u8bc1|\u8d22\u52a1|\u4fdd\u7ba1|\u7f16\u5236|\u6587\u6863|\u534f\u52a9|\u7269\u8d44|\u884c\u653f\u5de5\u4f5c|\u767b\u8bb0|\u65bd\u5de5\u73b0\u573a|\u8d44\u6599\u5458|\u8d44\u6599\u7ba1\u7406|\u65bd\u5de5\u56fe", "id": "u3322"}], "links": [{"label": "hasSubType", "source": "j47415", "target": "front desk"}, {"label": "interactedBy", "source": "j115425", "target": "u3322"}, {"label": "hasSubType", "source": "j145676", "target": "reception"}, {"label": "hasSubType", "source": "j117038", "target": "front desk"}, {"label": "isSubTypeOf", "source": "front desk", "target": "j14372"}, {"label": "isSubTypeOf", "source": "front desk", "target": "j145676"}, {"label": "isSubTypeOf", "source": "reception", "target": "j14372"}, {"label": "interactedWith", "source": "u3322", "target": "j117038"}, {"label": "interactedWith", "source": "u3322", "target": "j47415"}, {"label": "interactedWith", "source": "u3322", "target": "j115425"}]}, "j211438": {"directed": true, "multigraph": false, "graph": {}, "nodes": [{"id": "HR Specialist"}, {"title": "\u4eba\u8d44\u4e13\u5458", "id": "j81286"}, {"title": "\u96c6\u56e2\u4eba\u8d44\u884c\u653f\u4e13\u5458", "id": "j3320"}, {"title": "\u529e\u516c\u6587\u5458[\u5317\u4eac]", "id": "j219979"}, {"id": "assistant"}, {"id": "clerk"}, {"title": "\u4eba\u4e8b\u52a9\u7406\uff08\u5e26\u85aa\u57f9\u8bad\uff0b\u4e94\u9669\u4e00\u91d1\uff0b\u5e26\u85aa\u4f11\u5047\uff09", "id": "j211438"}, {"experience": "\u4e92\u8054\u7f51\u53c2\u8003\u6a21\u578bosi\u4e03\u5c42|\u8d44\u6599\u5458\u4e0a\u5c97\u8bc1|\u64cd\u4f5c|\u8d44\u6599|\u4eba\u4e8b\u884c\u653f|\u540e\u53f0|\u9500\u552e\u6280\u80fd|\u7b7e\u8bc1|\u8d22\u52a1|\u4fdd\u7ba1|\u7f16\u5236|\u6587\u6863|\u534f\u52a9|\u7269\u8d44|\u884c\u653f\u5de5\u4f5c|\u767b\u8bb0|\u65bd\u5de5\u73b0\u573a|\u8d44\u6599\u5458|\u8d44\u6599\u7ba1\u7406|\u65bd\u5de5\u56fe", "id": "u3322"}], "links": [{"label": "isSubTypeOf", "source": "HR Specialist", "target": "j81286"}, {"label": "hasSubType", "source": "j81286", "target": "assistant"}, {"label": "hasSubType", "source": "j3320", "target": "HR Specialist"}, {"label": "hasSubType", "source": "j219979", "target": "clerk"}, {"label": "isSubTypeOf", "source": "assistant", "target": "j211438"}, {"label": "isSubTypeOf", "source": "clerk", "target": "j211438"}, {"label": "interactedWith", "source": "u3322", "target": "j219979"}, {"label": "interactedWith", "source": "u3322", "target": "j3320"}]}, "j117038": {"directed": true, "multigraph": false, "graph": {}, "nodes": [], "links": []}, "j90163": {"directed": true, "multigraph": false, "graph": {}, "nodes": [{"title": "\u6587\u54584k+\u53cc\u4f11+\u664b\u5347+\u4e94\u9669", "id": "j59689"}, {"title": "\u7ecf\u7406\u52a9\u7406\u5468\u672b\u53cc\u4f11", "id": "j216327"}, {"title": "\u4eba\u4e8b\u884c\u653f\u6587\u5458", "id": "j219750"}, {"id": "Administrative Commissioner"}, {"title": "\u529e\u516c\u6587\u5458\uff08\u65e9\u4e5d\u665a\u516d+\u53cc\u4f11\uff09", "id": "j90163"}, {"id": "Training Specialist"}, {"id": "assistant"}, {"id": "clerk"}, {"experience": "\u8d23\u4efb\u5fc3|\u5ba2\u670d\u4e13\u5458|\u81ea\u6211\u8bc4\u4ef7|\u5b9e\u4e60|\u5b66\u4e60\u80fd\u529b|\u5f55\u5165|\u7cfb\u7edf|\u540e\u671f|\u6c7d\u8f66\u884c\u4e1a|\u6838\u5bf9|\u7eed\u4fdd", "id": "u3694"}, {"id": "Data clerk employment certificate"}, {"title": "\u884c\u653f\u6587\u5458", "id": "j223950"}, {"title": "\u57f9\u8bad\u4e13\u5458", "id": "j98396"}, {"experience": "\u4e92\u8054\u7f51\u53c2\u8003\u6a21\u578bosi\u4e03\u5c42|\u8d44\u6599\u5458\u4e0a\u5c97\u8bc1|\u64cd\u4f5c|\u8d44\u6599|\u4eba\u4e8b\u884c\u653f|\u540e\u53f0|\u9500\u552e\u6280\u80fd|\u7b7e\u8bc1|\u8d22\u52a1|\u4fdd\u7ba1|\u7f16\u5236|\u6587\u6863|\u534f\u52a9|\u7269\u8d44|\u884c\u653f\u5de5\u4f5c|\u767b\u8bb0|\u65bd\u5de5\u73b0\u573a|\u8d44\u6599\u5458|\u8d44\u6599\u7ba1\u7406|\u65bd\u5de5\u56fe", "id": "u3322"}], "links": [{"label": "hasSubType", "source": "j59689", "target": "clerk"}, {"label": "hasSubType", "source": "j216327", "target": "Training Specialist"}, {"label": "hasSubType", "source": "j219750", "target": "Administrative Commissioner"}, {"label": "isSubTypeOf", "source": "Administrative Commissioner", "target": "j223950"}, {"label": "isSubTypeOf", "source": "Training Specialist", "target": "j98396"}, {"label": "isSubTypeOf", "source": "assistant", "target": "j90163"}, {"label": "isSubTypeOf", "source": "clerk", "target": "j90163"}, {"label": "interactedWith", "source": "u3694", "target": "j59689"}, {"label": "isHeldBy", "source": "Data clerk employment certificate", "target": "u3322"}, {"label": "interactedBy", "source": "j223950", "target": "u3694"}, {"label": "hasSubType", "source": "j98396", "target": "assistant"}, {"label": "interactedWith", "source": "u3322", "target": "j216327"}, {"label": "interactedWith", "source": "u3322", "target": "j219750"}, {"label": "hasSkill", "source": "u3322", "target": "Data clerk employment certificate"}]}, "8d5df3e11f3c24378c23221e29e59573": {"directed": true, "multigraph": false, "graph": {}, "nodes": [], "links": []}, "j28993": {"directed": true, "multigraph": false, "graph": {}, "nodes": [{"id": "assistant"}, {"id": "HR Specialist"}, {"title": "\u884c\u653f\u4eba\u4e8b\u4e13\u5458", "id": "j28993"}, {"title": "\u84dd\u6708\u4eae\u8bda\u8058\u5510\u5c71\u4eba\u4e8b\u4e13\u5458", "id": "j206488"}, {"experience": "\u4e92\u8054\u7f51\u53c2\u8003\u6a21\u578bosi\u4e03\u5c42|\u8d44\u6599\u5458\u4e0a\u5c97\u8bc1|\u64cd\u4f5c|\u8d44\u6599|\u4eba\u4e8b\u884c\u653f|\u540e\u53f0|\u9500\u552e\u6280\u80fd|\u7b7e\u8bc1|\u8d22\u52a1|\u4fdd\u7ba1|\u7f16\u5236|\u6587\u6863|\u534f\u52a9|\u7269\u8d44|\u884c\u653f\u5de5\u4f5c|\u767b\u8bb0|\u65bd\u5de5\u73b0\u573a|\u8d44\u6599\u5458|\u8d44\u6599\u7ba1\u7406|\u65bd\u5de5\u56fe", "id": "u3322"}], "links": [{"label": "isSubTypeOf", "source": "assistant", "target": "j28993"}, {"label": "isSubTypeOf", "source": "HR Specialist", "target": "j28993"}, {"label": "hasSubType", "source": "j206488", "target": "HR Specialist"}, {"label": "hasSubType", "source": "j206488", "target": "assistant"}, {"label": "interactedWith", "source": "u3322", "target": "j206488"}]}, "j253652": {"directed": true, "multigraph": false, "graph": {}, "nodes": [], "links": []}, "j253243": {"directed": true, "multigraph": false, "graph": {}, "nodes": [{"experience": "\u4e92\u8054\u7f51\u53c2\u8003\u6a21\u578bosi\u4e03\u5c42|\u8d44\u6599\u5458\u4e0a\u5c97\u8bc1|\u64cd\u4f5c|\u8d44\u6599|\u4eba\u4e8b\u884c\u653f|\u540e\u53f0|\u9500\u552e\u6280\u80fd|\u7b7e\u8bc1|\u8d22\u52a1|\u4fdd\u7ba1|\u7f16\u5236|\u6587\u6863|\u534f\u52a9|\u7269\u8d44|\u884c\u653f\u5de5\u4f5c|\u767b\u8bb0|\u65bd\u5de5\u73b0\u573a|\u8d44\u6599\u5458|\u8d44\u6599\u7ba1\u7406|\u65bd\u5de5\u56fe", "id": "u3322"}, {"title": "\u5185\u52e4", "id": "j25748"}, {"id": "Insurance back office"}, {"title": "\u94f6\u4fdd\u7efc\u5408\u5185\u52e4\u5c97", "id": "j53475"}, {"title": "\u5510\u5c71\u4e2d\u652f\u8d22\u52a1\u90e8-\u7efc\u5408\u7ba1\u7406\u5c97", "id": "j253243"}], "links": [{"label": "interactedWith", "source": "u3322", "target": "j25748"}, {"label": "interactedWith", "source": "u3322", "target": "j53475"}, {"label": "interactedBy", "source": "j25748", "target": "u3322"}, {"label": "isSubTypeOf", "source": "Insurance back office", "target": "j253243"}, {"label": "hasSubType", "source": "j53475", "target": "Insurance back office"}]}, "j206488": {"directed": true, "multigraph": false, "graph": {}, "nodes": [{"id": "assistant"}, {"title": "\u529e\u516c\u5ba4\u6587\u5458", "id": "j80551"}, {"id": "HR Specialist"}, {"title": "\u884c\u653f\u4e13\u5458", "id": "j260948"}, {"title": "\u84dd\u6708\u4eae\u8bda\u8058\u5510\u5c71\u4eba\u4e8b\u4e13\u5458", "id": "j206488"}, {"experience": "\u4e92\u8054\u7f51\u53c2\u8003\u6a21\u578bosi\u4e03\u5c42|\u8d44\u6599\u5458\u4e0a\u5c97\u8bc1|\u64cd\u4f5c|\u8d44\u6599|\u4eba\u4e8b\u884c\u653f|\u540e\u53f0|\u9500\u552e\u6280\u80fd|\u7b7e\u8bc1|\u8d22\u52a1|\u4fdd\u7ba1|\u7f16\u5236|\u6587\u6863|\u534f\u52a9|\u7269\u8d44|\u884c\u653f\u5de5\u4f5c|\u767b\u8bb0|\u65bd\u5de5\u73b0\u573a|\u8d44\u6599\u5458|\u8d44\u6599\u7ba1\u7406|\u65bd\u5de5\u56fe", "id": "u3322"}, {"title": "\u4eba\u4e8b\u884c\u653f", "id": "j154254"}], "links": [{"label": "isSubTypeOf", "source": "assistant", "target": "j154254"}, {"label": "isSubTypeOf", "source": "assistant", "target": "j206488"}, {"label": "hasSubType", "source": "j80551", "target": "assistant"}, {"label": "isSubTypeOf", "source": "HR Specialist", "target": "j206488"}, {"label": "hasSubType", "source": "j260948", "target": "assistant"}, {"label": "interactedWith", "source": "u3322", "target": "j80551"}, {"label": "interactedWith", "source": "u3322", "target": "j260948"}, {"label": "hasSubType", "source": "j154254", "target": "HR Specialist"}]}, "j62198": {"directed": true, "multigraph": false, "graph": {}, "nodes": [{"id": "assistant"}, {"title": "\u529e\u516c\u5ba4\u6587\u5458", "id": "j80551"}, {"id": "Administrative Commissioner"}, {"title": "\u5468\u672b\u53cc\u4f11\u4eba\u4e8b\u4e13\u5458\u52a9\u7406", "id": "j62198"}, {"experience": "\u4e92\u8054\u7f51\u53c2\u8003\u6a21\u578bosi\u4e03\u5c42|\u8d44\u6599\u5458\u4e0a\u5c97\u8bc1|\u64cd\u4f5c|\u8d44\u6599|\u4eba\u4e8b\u884c\u653f|\u540e\u53f0|\u9500\u552e\u6280\u80fd|\u7b7e\u8bc1|\u8d22\u52a1|\u4fdd\u7ba1|\u7f16\u5236|\u6587\u6863|\u534f\u52a9|\u7269\u8d44|\u884c\u653f\u5de5\u4f5c|\u767b\u8bb0|\u65bd\u5de5\u73b0\u573a|\u8d44\u6599\u5458|\u8d44\u6599\u7ba1\u7406|\u65bd\u5de5\u56fe", "id": "u3322"}, {"title": "\u884c\u653f\u4e13\u5458", "id": "j219021"}], "links": [{"label": "isSubTypeOf", "source": "assistant", "target": "j62198"}, {"label": "hasSubType", "source": "j80551", "target": "assistant"}, {"label": "isSubTypeOf", "source": "Administrative Commissioner", "target": "j62198"}, {"label": "interactedWith", "source": "u3322", "target": "j219021"}, {"label": "interactedWith", "source": "u3322", "target": "j80551"}, {"label": "hasSubType", "source": "j219021", "target": "Administrative Commissioner"}]}, "j113635": {"directed": true, "multigraph": false, "graph": {}, "nodes": [{"id": "assistant"}, {"title": "\u5510\u5c71\u5206\u516c\u53f8\u5185\u52e4", "id": "j239730"}, {"id": "Administrative Commissioner"}, {"title": "\u524d\u53f0\u6587\u5458", "id": "j165342"}, {"title": "\u6587\u5458\u63d0\u4f9b\u4f4f\u5bbf", "id": "j113635"}, {"experience": "\u4e92\u8054\u7f51\u53c2\u8003\u6a21\u578bosi\u4e03\u5c42|\u8d44\u6599\u5458\u4e0a\u5c97\u8bc1|\u64cd\u4f5c|\u8d44\u6599|\u4eba\u4e8b\u884c\u653f|\u540e\u53f0|\u9500\u552e\u6280\u80fd|\u7b7e\u8bc1|\u8d22\u52a1|\u4fdd\u7ba1|\u7f16\u5236|\u6587\u6863|\u534f\u52a9|\u7269\u8d44|\u884c\u653f\u5de5\u4f5c|\u767b\u8bb0|\u65bd\u5de5\u73b0\u573a|\u8d44\u6599\u5458|\u8d44\u6599\u7ba1\u7406|\u65bd\u5de5\u56fe", "id": "u3322"}], "links": [{"label": "isSubTypeOf", "source": "assistant", "target": "j113635"}, {"label": "interactedBy", "source": "j239730", "target": "u3322"}, {"label": "isSubTypeOf", "source": "Administrative Commissioner", "target": "j165342"}, {"label": "hasSubType", "source": "j165342", "target": "assistant"}, {"label": "interactedWith", "source": "u3322", "target": "j239730"}, {"label": "wantsType", "source": "u3322", "target": "Administrative Commissioner"}]}, "j47155": {"directed": true, "multigraph": false, "graph": {}, "nodes": [{"id": "assistant"}, {"experience": "\u4e92\u8054\u7f51\u53c2\u8003\u6a21\u578bosi\u4e03\u5c42|\u8d44\u6599\u5458\u4e0a\u5c97\u8bc1|\u64cd\u4f5c|\u8d44\u6599|\u4eba\u4e8b\u884c\u653f|\u540e\u53f0|\u9500\u552e\u6280\u80fd|\u7b7e\u8bc1|\u8d22\u52a1|\u4fdd\u7ba1|\u7f16\u5236|\u6587\u6863|\u534f\u52a9|\u7269\u8d44|\u884c\u653f\u5de5\u4f5c|\u767b\u8bb0|\u65bd\u5de5\u73b0\u573a|\u8d44\u6599\u5458|\u8d44\u6599\u7ba1\u7406|\u65bd\u5de5\u56fe", "id": "u3322"}, {"title": "\u529e\u516c\u5ba4\u6587\u5458", "id": "j47155"}, {"title": "\u884c\u653f\u4eba\u4e8b\u4e13\u5458", "id": "j28993"}], "links": [{"label": "isSubTypeOf", "source": "assistant", "target": "j47155"}, {"label": "interactedWith", "source": "u3322", "target": "j28993"}, {"label": "hasSubType", "source": "j28993", "target": "assistant"}]}, "j236220": {"directed": true, "multigraph": false, "graph": {}, "nodes": [], "links": []}, "j160788": {"directed": true, "multigraph": false, "graph": {}, "nodes": [{"title": "\u4eba\u4e8b\u884c\u653f\u4e13\u5458", "id": "j219480"}, {"title": "\u8fd0\u8425\u90e8\u524d\u53f0\u63a5\u5f85", "id": "j47415"}, {"id": "front desk"}, {"experience": "\u4e92\u8054\u7f51\u53c2\u8003\u6a21\u578bosi\u4e03\u5c42|\u8d44\u6599\u5458\u4e0a\u5c97\u8bc1|\u64cd\u4f5c|\u8d44\u6599|\u4eba\u4e8b\u884c\u653f|\u540e\u53f0|\u9500\u552e\u6280\u80fd|\u7b7e\u8bc1|\u8d22\u52a1|\u4fdd\u7ba1|\u7f16\u5236|\u6587\u6863|\u534f\u52a9|\u7269\u8d44|\u884c\u653f\u5de5\u4f5c|\u767b\u8bb0|\u65bd\u5de5\u73b0\u573a|\u8d44\u6599\u5458|\u8d44\u6599\u7ba1\u7406|\u65bd\u5de5\u56fe", "id": "u3322"}, {"title": "\u524d\u53f0\u63a5\u5f85\u6587\u804c", "id": "j160788"}], "links": [{"label": "interactedBy", "source": "j219480", "target": "u3322"}, {"label": "hasSubType", "source": "j47415", "target": "front desk"}, {"label": "isSubTypeOf", "source": "front desk", "target": "j160788"}, {"label": "interactedWith", "source": "u3322", "target": "j47415"}, {"label": "interactedWith", "source": "u3322", "target": "j219480"}]}, "j75715": {"directed": true, "multigraph": false, "graph": {}, "nodes": [{"id": "assistant"}, {"title": "\u884c\u653f\u4eba\u4e8b\u4e13\u5458", "id": "j42760"}, {"experience": "\u4e92\u8054\u7f51\u53c2\u8003\u6a21\u578bosi\u4e03\u5c42|\u8d44\u6599\u5458\u4e0a\u5c97\u8bc1|\u64cd\u4f5c|\u8d44\u6599|\u4eba\u4e8b\u884c\u653f|\u540e\u53f0|\u9500\u552e\u6280\u80fd|\u7b7e\u8bc1|\u8d22\u52a1|\u4fdd\u7ba1|\u7f16\u5236|\u6587\u6863|\u534f\u52a9|\u7269\u8d44|\u884c\u653f\u5de5\u4f5c|\u767b\u8bb0|\u65bd\u5de5\u73b0\u573a|\u8d44\u6599\u5458|\u8d44\u6599\u7ba1\u7406|\u65bd\u5de5\u56fe", "id": "u3322"}, {"title": "\u90e8\u95e8\u52a9\u7406/\u63d0\u4f9b\u5348\u9910", "id": "j75715"}], "links": [{"label": "isSubTypeOf", "source": "assistant", "target": "j75715"}, {"label": "hasSubType", "source": "j42760", "target": "assistant"}, {"label": "interactedWith", "source": "u3322", "target": "j42760"}]}, "j143990": {"directed": true, "multigraph": false, "graph": {}, "nodes": [{"id": "educate"}, {"title": "\u4eba\u529b\u8d44\u6e90\u4e13\u5458", "id": "j143990"}, {"id": "Administrative Commissioner"}, {"id": "system"}, {"id": "assistant"}, {"title": "\u8bda\u8058\u884c\u653f\u4e13\u5458\u6587\u5458", "id": "j217650"}, {"experience": "\u8ba1\u5212|\u79d8\u4e66|\u4e92\u8054\u7f51\u53c2\u8003\u6a21\u578bosi\u4e03\u5c42|ps|\u529e\u516c|\u8425\u4e1a|office|\u5408\u540c|\u4fdd\u8bc1|\u8d23\u4efb\u5fc3|\u4fe1\u606f\u7ba1\u7406\u4e0e\u4fe1\u606f\u7cfb\u7edf|\u6570\u636e\u7edf\u8ba1\u5206\u6790|\u7f8e\u5bb9\u5e08|\u7ecf\u7406|\u751f\u4ea7\u7ba1\u7406|\u90ae\u4ef6|\u8d44\u91d1|\u536b\u751f|\u534f\u8c03|\u9644\u4ef6|\u5b89\u6392|\u64cd\u4f5c|\u9886\u5bfc|\u56de\u8bbf|\u7edf\u8ba1|\u8d22\u52a1|\u5e93\u5b58|\u6587\u6863|\u516c\u4ea4|\u5b66\u4e60\u80fd\u529b|\u5f55\u5165|\u9500\u552e|\u8fdb\u8d27|\u6587\u5458|\u7ef4\u62a4|\u9500\u552e\u90e8|\u5206\u6790|\u4f63\u91d1|\u5165\u5e93|\u6863\u6848|\u6267\u884c|\u4e34\u65f6|\u7cfb\u7edf|\u9500\u552e\u7ecf\u7406|\u6838\u7b97|\u91c7\u8d2d|\u5f52\u6863|\u8ba2\u8d2d|\u8d44\u6e90|\u8d44\u6599\u7ba1\u7406|\u5ba2\u6237|\u8ba2\u5355|\u8bd5\u4e58\u8bd5\u9a7e|\u751f\u4ea7|\u6d41\u7a0b|\u8d22\u52a1\u7ba1\u7406|\u4fdd\u7ba1|\u62a5\u8868|\u4eb2\u548c\u529b|\u6253\u5370|\u8f66\u8f86|\u6570\u636e|\u7535\u8111|\u5e02\u573a|\u4ea7\u54c1|\u5185\u52e4|\u8f6f\u4ef6|\u76d1\u63a7|\u9002\u5e94\u80fd\u529b|\u8ba2\u5355\u7ba1\u7406|\u4fe1\u606f\u7ba1\u7406|\u65e5\u5e38\u7ba1\u7406|\u8d22\u52a1\u7ecf\u7406|photoshop\uff08ps\uff09\u56fe\u50cf\u5904\u7406\u8f6f\u4ef6", "id": "u3061"}, {"experience": "\u4e13\u67dc|\u9500\u552e\u5546|\u7a97\u53e3|\u7efc\u5408|\u5e97\u957f|\u53d7\u7406|\u6863\u6848|\u5904\u7406|\u8d27\u54c1|\u7cfb\u7edf|\u7ec4\u7ec7|\u5ba2\u8bc9|\u5bfc\u8d2d\u5458|\u534f\u8c03\u80fd\u529b|\u4e1a\u52a1|\u6d3e\u9001|\u5e97\u94fa|\u54a8\u8be2|\u5b66\u4e60|\u6c9f\u901a\u80fd\u529b|\u50a8\u5907|\u6c9f\u901a|\u8fd0\u4f5c", "id": "u3250"}, {"experience": "\u4e92\u8054\u7f51\u53c2\u8003\u6a21\u578bosi\u4e03\u5c42|\u8d44\u6599\u5458\u4e0a\u5c97\u8bc1|\u64cd\u4f5c|\u8d44\u6599|\u4eba\u4e8b\u884c\u653f|\u540e\u53f0|\u9500\u552e\u6280\u80fd|\u7b7e\u8bc1|\u8d22\u52a1|\u4fdd\u7ba1|\u7f16\u5236|\u6587\u6863|\u534f\u52a9|\u7269\u8d44|\u884c\u653f\u5de5\u4f5c|\u767b\u8bb0|\u65bd\u5de5\u73b0\u573a|\u8d44\u6599\u5458|\u8d44\u6599\u7ba1\u7406|\u65bd\u5de5\u56fe", "id": "u3322"}], "links": [{"label": "isWantedIndustryOf", "source": "educate", "target": "u3250"}, {"label": "isSubTypeOf", "source": "Administrative Commissioner", "target": "j217650"}, {"label": "isHeldBy", "source": "system", "target": "u3061"}, {"label": "isSubTypeOf", "source": "assistant", "target": "j143990"}, {"label": "hasSubType", "source": "j217650", "target": "assistant"}, {"label": "wantsType", "source": "u3061", "target": "Administrative Commissioner"}, {"label": "hasSkill", "source": "u3250", "target": "system"}, {"label": "wantsIndustry", "source": "u3322", "target": "educate"}]}, "j84419": {"directed": true, "multigraph": false, "graph": {}, "nodes": [{"title": "\u884c\u653f\u652f\u6301\u5510\u5c71\u516c\u53f8-\u5357\u6e56CBD\u9879\u76ee\u90e8", "id": "j92936"}, {"title": "\u4e94\u9669\u4e00\u91d1\u5e95\u85aa3.5K\u8058\u9a7b\u573a\uff08\u7f6e\u4e1a\u987e\u95ee\u5347\u7ea7\u7248\uff09", "id": "j178584"}, {"title": "\u8425\u9500\u4e3b\u7ba1", "id": "j168482"}, {"id": "real estate back office"}, {"id": "\\N"}, {"title": "\u623f\u8d37\u52a9\u7406", "id": "j84419"}, {"experience": "\u4e92\u8054\u7f51\u53c2\u8003\u6a21\u578bosi\u4e03\u5c42|\u8d44\u6599\u5458\u4e0a\u5c97\u8bc1|\u64cd\u4f5c|\u8d44\u6599|\u4eba\u4e8b\u884c\u653f|\u540e\u53f0|\u9500\u552e\u6280\u80fd|\u7b7e\u8bc1|\u8d22\u52a1|\u4fdd\u7ba1|\u7f16\u5236|\u6587\u6863|\u534f\u52a9|\u7269\u8d44|\u884c\u653f\u5de5\u4f5c|\u767b\u8bb0|\u65bd\u5de5\u73b0\u573a|\u8d44\u6599\u5458|\u8d44\u6599\u7ba1\u7406|\u65bd\u5de5\u56fe", "id": "u3322"}, {"experience": "\u4e92\u8054\u7f51\u53c2\u8003\u6a21\u578bosi\u4e03\u5c42|\u73b0\u573a|\u552e\u697c|\u6309\u63ed|\u5de5\u4f5c\u5c97\u4f4d|office|\u7ec4\u7ec7|\u63a5\u5f85|\u8c08\u5224|\u5c55\u793a|\u77e5\u8bc6|\u8d23\u4efb\u5fc3|\u623f\u4ea7\u9500\u552e|\u5feb\u901f|\u767b\u8bb0|\u54c1\u724c|\u65b9\u6848|\u51fa\u53e3|\u7559\u5b66|\u7f51\u7ad9|\u9500\u552e\u6280\u80fd|\u5916\u56fd|\u5b66\u4e60|\u5546\u54c1|\u8bbe\u8ba1|\u56fd\u5916|\u56e2\u961f\u9886\u5bfc|\u9080\u7ea6|\u7f6e\u4e1a\u987e\u95ee|\u9500\u552e|\u6d3b\u52a8|\u623f\u4ea7|\u5ba2\u6237\u5f00\u53d1|\u4e1a\u52a1|\u697c\u76d8|\u51fa\u53e3\u8d38\u6613|\u4e1a\u52a1\u5458|\u5ba2\u6237|\u623f\u5c4b\u4e70\u5356|\u5173\u7cfb|\u9500\u552e\u80fd\u529b|\u6d41\u7a0b|\u7b7e\u7ea6|\u5916\u8d38|\u6280\u5de7|\u62d3\u5c55|\u8bba\u575b|\u9500\u552e\u4e1a\u52a1|\u5b66\u751f|\u7b56\u5212|\u4ea7\u54c1|\u8d37\u6b3e|\u524d\u671f|\u5fae\u4fe1|\u79fb\u6c11|\u552e\u697c\u5904|\u653f\u7b56|\u5e02\u573a\u8c03\u7814|\u62a5\u4ef7", "id": "u383"}], "links": [{"label": "hasSubType", "source": "j92936", "target": "real estate back office"}, {"label": "interactedBy", "source": "j178584", "target": "u383"}, {"label": "hasSubType", "source": "j168482", "target": "\\N"}, {"label": "isSubTypeOf", "source": "real estate back office", "target": "j178584"}, {"label": "isSubTypeOf", "source": "\\N", "target": "j84419"}, {"label": "interactedWith", "source": "u3322", "target": "j92936"}, {"label": "interactedWith", "source": "u383", "target": "j168482"}]}, "j92244": {"directed": true, "multigraph": false, "graph": {}, "nodes": [], "links": []}, "j257041": {"directed": true, "multigraph": false, "graph": {}, "nodes": [{"title": "\u884c\u653f\u52a9\u7406", "id": "j249374"}, {"title": "\u9879\u76ee\u52a9\u7406\u623f\u5730\u4ea7\u5185\u52e4", "id": "j67937"}, {"title": "\u5185\u52e4\u52a9\u7406", "id": "j79797"}, {"id": "secretary"}, {"title": "\u94f6\u4fdd\u7efc\u5408\u5185\u52e4\u5c97", "id": "j53475"}, {"id": "assistant"}, {"title": "\u8463\u4e8b\u957f\u52a9\u7406", "id": "j257041"}, {"experience": "\u4e92\u8054\u7f51\u53c2\u8003\u6a21\u578bosi\u4e03\u5c42|\u8d44\u6599\u5458\u4e0a\u5c97\u8bc1|\u64cd\u4f5c|\u8d44\u6599|\u4eba\u4e8b\u884c\u653f|\u540e\u53f0|\u9500\u552e\u6280\u80fd|\u7b7e\u8bc1|\u8d22\u52a1|\u4fdd\u7ba1|\u7f16\u5236|\u6587\u6863|\u534f\u52a9|\u7269\u8d44|\u884c\u653f\u5de5\u4f5c|\u767b\u8bb0|\u65bd\u5de5\u73b0\u573a|\u8d44\u6599\u5458|\u8d44\u6599\u7ba1\u7406|\u65bd\u5de5\u56fe", "id": "u3322"}], "links": [{"label": "hasSubType", "source": "j249374", "target": "assistant"}, {"label": "interactedBy", "source": "j67937", "target": "u3322"}, {"label": "hasSubType", "source": "j79797", "target": "secretary"}, {"label": "isSubTypeOf", "source": "secretary", "target": "j257041"}, {"label": "interactedBy", "source": "j53475", "target": "u3322"}, {"label": "isSubTypeOf", "source": "assistant", "target": "j257041"}, {"label": "interactedWith", "source": "u3322", "target": "j249374"}, {"label": "interactedWith", "source": "u3322", "target": "j67937"}, {"label": "interactedWith", "source": "u3322", "target": "j79797"}, {"label": "interactedWith", "source": "u3322", "target": "j53475"}]}, "j231726": {"directed": true, "multigraph": false, "graph": {}, "nodes": [], "links": []}, "j142700": {"directed": true, "multigraph": false, "graph": {}, "nodes": [], "links": []}, "j219021": {"directed": true, "multigraph": false, "graph": {}, "nodes": [{"id": "assistant"}, {"experience": "\u4e92\u8054\u7f51\u53c2\u8003\u6a21\u578bosi\u4e03\u5c42|\u8d44\u6599\u5458\u4e0a\u5c97\u8bc1|\u64cd\u4f5c|\u8d44\u6599|\u4eba\u4e8b\u884c\u653f|\u540e\u53f0|\u9500\u552e\u6280\u80fd|\u7b7e\u8bc1|\u8d22\u52a1|\u4fdd\u7ba1|\u7f16\u5236|\u6587\u6863|\u534f\u52a9|\u7269\u8d44|\u884c\u653f\u5de5\u4f5c|\u767b\u8bb0|\u65bd\u5de5\u73b0\u573a|\u8d44\u6599\u5458|\u8d44\u6599\u7ba1\u7406|\u65bd\u5de5\u56fe", "id": "u3322"}, {"title": "\u884c\u653f\u4e13\u5458", "id": "j219021"}], "links": [{"label": "isSubTypeOf", "source": "assistant", "target": "j219021"}, {"label": "wantsType", "source": "u3322", "target": "assistant"}]}, "j32018": {"directed": true, "multigraph": false, "graph": {}, "nodes": [], "links": []}, "j157410": {"directed": true, "multigraph": false, "graph": {}, "nodes": [{"title": "\u4eba\u8d44\u884c\u653f\u4e13\u5458", "id": "j157410"}, {"id": "assistant"}, {"title": "\u529e\u516c\u5ba4\u6587\u5458", "id": "j80551"}, {"id": "HR Specialist"}, {"title": "\u884c\u653f\u4e13\u5458", "id": "j263404"}, {"experience": "\u4e92\u8054\u7f51\u53c2\u8003\u6a21\u578bosi\u4e03\u5c42|\u8d44\u6599\u5458\u4e0a\u5c97\u8bc1|\u64cd\u4f5c|\u8d44\u6599|\u4eba\u4e8b\u884c\u653f|\u540e\u53f0|\u9500\u552e\u6280\u80fd|\u7b7e\u8bc1|\u8d22\u52a1|\u4fdd\u7ba1|\u7f16\u5236|\u6587\u6863|\u534f\u52a9|\u7269\u8d44|\u884c\u653f\u5de5\u4f5c|\u767b\u8bb0|\u65bd\u5de5\u73b0\u573a|\u8d44\u6599\u5458|\u8d44\u6599\u7ba1\u7406|\u65bd\u5de5\u56fe", "id": "u3322"}], "links": [{"label": "isSubTypeOf", "source": "assistant", "target": "j157410"}, {"label": "hasSubType", "source": "j80551", "target": "assistant"}, {"label": "isSubTypeOf", "source": "HR Specialist", "target": "j157410"}, {"label": "hasSubType", "source": "j263404", "target": "HR Specialist"}, {"label": "interactedWith", "source": "u3322", "target": "j80551"}, {"label": "interactedWith", "source": "u3322", "target": "j263404"}]}, "j140124": {"directed": true, "multigraph": false, "graph": {}, "nodes": [], "links": []}, "b131dd45df3298b0696df84a660a53c6": {"directed": true, "multigraph": false, "graph": {}, "nodes": [{"title": "\u6587\u5458", "id": "j85426"}, {"experience": "\u4e92\u8054\u7f51\u53c2\u8003\u6a21\u578bosi\u4e03\u5c42|\u8d44\u6599\u5458\u4e0a\u5c97\u8bc1|\u64cd\u4f5c|\u8d44\u6599|\u4eba\u4e8b\u884c\u653f|\u540e\u53f0|\u9500\u552e\u6280\u80fd|\u7b7e\u8bc1|\u8d22\u52a1|\u4fdd\u7ba1|\u7f16\u5236|\u6587\u6863|\u534f\u52a9|\u7269\u8d44|\u884c\u653f\u5de5\u4f5c|\u767b\u8bb0|\u65bd\u5de5\u73b0\u573a|\u8d44\u6599\u5458|\u8d44\u6599\u7ba1\u7406|\u65bd\u5de5\u56fe", "id": "u3322"}], "links": [{"label": "interactedBy", "source": "j85426", "target": "u3322"}, {"label": "interactedWith", "source": "u3322", "target": "j85426"}]}}